{
  "single_boundary_updates_found": 6,
  "updates_by_hunt_code": {
    "DS6625": "10003",
    "EA1180": "684",
    "EA1270": "175",
    "EA1271": "51",
    "EA2041": "29",
    "EB3209": "683"
  },
  "file_row_changes": [
    {
      "file": "pipeline\\RAW\\hunt_unit_database\\2026\\csv\\DATABASE.csv",
      "rows_changed": 5
    },
    {
      "file": "processed_data\\hunt_master_enriched.csv",
      "rows_changed": 10
    },
    {
      "file": "processed_data\\hunt_unit_reference_linked.csv",
      "rows_changed": 12
    },
    {
      "file": "processed_data\\draw_reality_engine.csv",
      "rows_changed": 12
    },
    {
      "file": "processed_data\\point_ladder_view.csv",
      "rows_changed": 396
    },
    {
      "file": "processed_data\\hunt_boundary_crosswalk_2026.csv",
      "rows_changed": 5
    }
  ],
  "geometry_files_written": [
    "processed_data/boundaries/10003.geojson",
    "processed_data/boundaries/684.geojson",
    "processed_data/boundaries/175.geojson",
    "processed_data/boundaries/51.geojson",
    "processed_data/boundaries/29.geojson",
    "processed_data/boundaries/683.geojson"
  ],
  "geometry_files_written_count": 6
}