{
  "generated_at": "2026-05-29T17:09:54.068Z",
  "public_feed_rows": 0,
  "internal_feed_rows": 11,
  "readiness_status_counts": {
    "HOLD_INTERNAL_ONLY": 11
  },
  "risk_flag_counts": {
    "not_in_public_feed": 11,
    "normalization_only": 11,
    "no_review_date": 11,
    "no_unit_coverage": 1
  },
  "required_fields": [
    "outfitter_id",
    "display_name",
    "designation",
    "status",
    "species",
    "units",
    "services",
    "contact",
    "website",
    "phone",
    "email",
    "reviewed_at",
    "source_evidence_count",
    "insurance_or_license_notes",
    "federal_permit_units",
    "service_types",
    "public_profile_ready",
    "missing_fields",
    "risk_flags"
  ],
  "records": [
    {
      "outfitter_id": "wild-eyez-outfitters",
      "display_name": "Wild Eyez Outfitters",
      "designation": "CPO",
      "status": "Vetted",
      "species": "Elk|Deer",
      "units": "Beaver, East|Fishlake/Thousand Lakes|Fillmore, Pahvant|Manti|Manti/San Rafael|Monroe|Nebo|Nebo/San Pitch Mtns",
      "services": "",
      "contact": "https://www.wildeyez.net|4358516480|tyler@wildeyez.net",
      "website": "https://www.wildeyez.net",
      "phone": "4358516480",
      "email": "tyler@wildeyez.net",
      "reviewed_at": "",
      "source_evidence_count": "",
      "insurance_or_license_notes": "Known-good trial row",
      "federal_permit_units": "Richfield|Fishlake NF - Richfield|Manti-La Sal NF - Sanpete",
      "service_types": "fully guided",
      "public_profile_ready": "false",
      "missing_fields": "reviewed_at|source_evidence_count",
      "risk_flags": "not_in_public_feed|normalization_only|no_review_date",
      "readiness_status": "HOLD_INTERNAL_ONLY",
      "source_feed": "internal"
    },
    {
      "outfitter_id": "albrecht-outfitters",
      "display_name": "Albrecht Outfitters",
      "designation": "Outfitter",
      "status": "Vetted",
      "species": "Deer",
      "units": "Fishlake|Boulder/Kaiparowits|Henry Mtns|Fillmore|Mt Dutton|Monroe|Beaver, East",
      "services": "",
      "contact": "https://albrechtoutfitting.com/|435-979-7227|tayloralbrecht@hotmail.com",
      "website": "https://albrechtoutfitting.com/",
      "phone": "435-979-7227",
      "email": "tayloralbrecht@hotmail.com",
      "reviewed_at": "",
      "source_evidence_count": "",
      "insurance_or_license_notes": "First-pass normalization only",
      "federal_permit_units": "Fishlake",
      "service_types": "fully guided|trophy hunt support",
      "public_profile_ready": "false",
      "missing_fields": "reviewed_at|source_evidence_count",
      "risk_flags": "not_in_public_feed|normalization_only|no_review_date",
      "readiness_status": "HOLD_INTERNAL_ONLY",
      "source_feed": "internal"
    },
    {
      "outfitter_id": "all-out-outfitters",
      "display_name": "All Out Outfitters",
      "designation": "Outfitter",
      "status": "Vetted",
      "species": "Deer",
      "units": "Fishlake|Boulder/Kaiparowits|Henry Mtns|Fillmore, Oak Creek LE|Mt Dutton|Monroe|Beaver, East",
      "services": "",
      "contact": "https://alloutoutfitters.net/|alloutoutfitters@gmail.com|alan.wood@ipsc.com",
      "website": "https://alloutoutfitters.net/",
      "phone": "",
      "email": "alloutoutfitters@gmail.com|alan.wood@ipsc.com",
      "reviewed_at": "",
      "source_evidence_count": "",
      "insurance_or_license_notes": "First-pass normalization only",
      "federal_permit_units": "Fishlake",
      "service_types": "fully guided|trophy hunt support",
      "public_profile_ready": "false",
      "missing_fields": "reviewed_at|source_evidence_count",
      "risk_flags": "not_in_public_feed|normalization_only|no_review_date",
      "readiness_status": "HOLD_INTERNAL_ONLY",
      "source_feed": "internal"
    },
    {
      "outfitter_id": "alpha-outfitters",
      "display_name": "Alpha Outfitters",
      "designation": "Outfitter",
      "status": "Vetted",
      "species": "Deer",
      "units": "Fishlake|Thousand Lakes|Boulder/Kaiparowits|Henry Mtns|Fillmore, Oak Creek LE|Mt Dutton|Monroe|Beaver, East|Manti/San Rafael",
      "services": "",
      "contact": "thealphaoutfitter@gmail.com",
      "website": "",
      "phone": "",
      "email": "thealphaoutfitter@gmail.com",
      "reviewed_at": "",
      "source_evidence_count": "",
      "insurance_or_license_notes": "First-pass normalization only",
      "federal_permit_units": "Grand Staircase Kanab|Duschene Dixie - Lake Powell Manti LaSal Fishlake",
      "service_types": "fully guided|trophy hunt support",
      "public_profile_ready": "false",
      "missing_fields": "reviewed_at|source_evidence_count",
      "risk_flags": "not_in_public_feed|normalization_only|no_review_date",
      "readiness_status": "HOLD_INTERNAL_ONLY",
      "source_feed": "internal"
    },
    {
      "outfitter_id": "apex-outfitters",
      "display_name": "Apex Outfitters",
      "designation": "Outfitter",
      "status": "Vetted",
      "species": "Deer",
      "units": "Manti/San Rafael|La Sal Mtns|Dolores Triangle",
      "services": "",
      "contact": "https://apexoutfitters.net/|435-749-0060|brettguymon77@gmail.com",
      "website": "https://apexoutfitters.net/",
      "phone": "435-749-0060",
      "email": "brettguymon77@gmail.com",
      "reviewed_at": "",
      "source_evidence_count": "",
      "insurance_or_license_notes": "First-pass normalization only",
      "federal_permit_units": "Manti LaSal",
      "service_types": "fully guided",
      "public_profile_ready": "false",
      "missing_fields": "reviewed_at|source_evidence_count",
      "risk_flags": "not_in_public_feed|normalization_only|no_review_date",
      "readiness_status": "HOLD_INTERNAL_ONLY",
      "source_feed": "internal"
    },
    {
      "outfitter_id": "apex-outfitters",
      "display_name": "Apex Outfitters",
      "designation": "Outfitter",
      "status": "Vetted",
      "species": "Elk",
      "units": "Manti|San Juan|La Sal Mtns|La Sal, Dolores Triangle",
      "services": "",
      "contact": "https://apexoutfitters.net/|435-749-0060|brettguymon77@gmail.com",
      "website": "https://apexoutfitters.net/",
      "phone": "435-749-0060",
      "email": "brettguymon77@gmail.com",
      "reviewed_at": "",
      "source_evidence_count": "",
      "insurance_or_license_notes": "First-pass normalization only",
      "federal_permit_units": "Manti LaSal",
      "service_types": "fully guided",
      "public_profile_ready": "false",
      "missing_fields": "reviewed_at|source_evidence_count",
      "risk_flags": "not_in_public_feed|normalization_only|no_review_date",
      "readiness_status": "HOLD_INTERNAL_ONLY",
      "source_feed": "internal"
    },
    {
      "outfitter_id": "battleground-g-o",
      "display_name": "Battleground G/O",
      "designation": "Outfitter",
      "status": "Vetted",
      "species": "Deer",
      "units": "Fishlake|Thousand Lakes|Boulder/Kaiparowits|Henry Mtns|Fillmore, Oak Creek LE|Mt Dutton|Monroe",
      "services": "",
      "contact": "801-647-5661|freedomrv@hotmail.com",
      "website": "",
      "phone": "801-647-5661",
      "email": "freedomrv@hotmail.com",
      "reviewed_at": "",
      "source_evidence_count": "",
      "insurance_or_license_notes": "First-pass normalization only",
      "federal_permit_units": "Fishlake",
      "service_types": "fully guided|trophy hunt support",
      "public_profile_ready": "false",
      "missing_fields": "reviewed_at|source_evidence_count",
      "risk_flags": "not_in_public_feed|normalization_only|no_review_date",
      "readiness_status": "HOLD_INTERNAL_ONLY",
      "source_feed": "internal"
    },
    {
      "outfitter_id": "beaver-mountain-outfitters",
      "display_name": "Beaver Mountain Outfitters",
      "designation": "Outfitter",
      "status": "Vetted",
      "species": "Deer",
      "units": "Fishlake|Thousand Lakes|Boulder/Kaiparowits|Henry Mtns|Fillmore, Oak Creek LE|Mt Dutton|Monroe|Beaver, East",
      "services": "",
      "contact": "https://www.facebook.com/profile.php?id=61576620110758#|435-421-1850|edwardsslade@gmail.com|aust4.ab@gmail.com",
      "website": "https://www.facebook.com/profile.php?id=61576620110758#",
      "phone": "435-421-1850",
      "email": "edwardsslade@gmail.com|aust4.ab@gmail.com",
      "reviewed_at": "",
      "source_evidence_count": "",
      "insurance_or_license_notes": "First-pass normalization only",
      "federal_permit_units": "Fishlake Dixie-Lake Powell",
      "service_types": "fully guided|trophy hunt support|OIL species support|mountain goat/sheep/high-country support",
      "public_profile_ready": "false",
      "missing_fields": "reviewed_at|source_evidence_count",
      "risk_flags": "not_in_public_feed|normalization_only|no_review_date",
      "readiness_status": "HOLD_INTERNAL_ONLY",
      "source_feed": "internal"
    },
    {
      "outfitter_id": "book-cliff-outfitters",
      "display_name": "Book Cliff Outfitters",
      "designation": "Outfitter",
      "status": "Vetted",
      "species": "Deer",
      "units": "",
      "services": "",
      "contact": "https://www.bookcliffoutfitters.com/|970.327.4787|tjpilling@gmail.com|bookcliffoutfitters77@gmail.com",
      "website": "https://www.bookcliffoutfitters.com/",
      "phone": "970.327.4787",
      "email": "tjpilling@gmail.com|bookcliffoutfitters77@gmail.com",
      "reviewed_at": "",
      "source_evidence_count": "",
      "insurance_or_license_notes": "First-pass normalization only",
      "federal_permit_units": "Grand Staircase Kanab|UWC",
      "service_types": "fully guided",
      "public_profile_ready": "false",
      "missing_fields": "units|reviewed_at|source_evidence_count",
      "risk_flags": "not_in_public_feed|normalization_only|no_unit_coverage|no_review_date",
      "readiness_status": "HOLD_INTERNAL_ONLY",
      "source_feed": "internal"
    },
    {
      "outfitter_id": "cisco-outfitting-travis-kruckenberg-outfitting",
      "display_name": "Cisco Outfitting Travis Kruckenberg Outfitting",
      "designation": "Outfitter",
      "status": "Vetted",
      "species": "Deer",
      "units": "Manti/San Rafael|La Sal Mtns|Dolores Triangle",
      "services": "",
      "contact": "https://www.traviskruckenbergoutfitting.com/|(970) 216-9694|traviskruckenberg@live.com",
      "website": "https://www.traviskruckenbergoutfitting.com/",
      "phone": "(970) 216-9694",
      "email": "traviskruckenberg@live.com",
      "reviewed_at": "",
      "source_evidence_count": "",
      "insurance_or_license_notes": "First-pass normalization only",
      "federal_permit_units": "Manti LaSal",
      "service_types": "fully guided",
      "public_profile_ready": "false",
      "missing_fields": "reviewed_at|source_evidence_count",
      "risk_flags": "not_in_public_feed|normalization_only|no_review_date",
      "readiness_status": "HOLD_INTERNAL_ONLY",
      "source_feed": "internal"
    },
    {
      "outfitter_id": "cisco-outfitting-travis-kruckenberg-outfitting",
      "display_name": "Cisco Outfitting Travis Kruckenberg Outfitting",
      "designation": "Outfitter",
      "status": "Vetted",
      "species": "Elk",
      "units": "Manti|San Juan|La Sal Mtns|La Sal, Dolores Triangle",
      "services": "",
      "contact": "https://www.traviskruckenbergoutfitting.com/|(970) 216-9694|traviskruckenberg@live.com",
      "website": "https://www.traviskruckenbergoutfitting.com/",
      "phone": "(970) 216-9694",
      "email": "traviskruckenberg@live.com",
      "reviewed_at": "",
      "source_evidence_count": "",
      "insurance_or_license_notes": "First-pass normalization only",
      "federal_permit_units": "Manti LaSal",
      "service_types": "fully guided",
      "public_profile_ready": "false",
      "missing_fields": "reviewed_at|source_evidence_count",
      "risk_flags": "not_in_public_feed|normalization_only|no_review_date",
      "readiness_status": "HOLD_INTERNAL_ONLY",
      "source_feed": "internal"
    }
  ]
}
