{
  "pending_count": 612,
  "modeled_count": 25771,
  "excluded_count": 4,
  "pending_by_draw_system": {
    "BEAR_DRAW": 83,
    "BONUS_CWMU_BIG_GAME": 383,
    "PREFERENCE_GENERAL_SEASON_BUCK_DEER": 132,
    "YOUTH_DRAW_ONLY_ELK": 2,
    "BONUS_ANTLERLESS_MOOSE": 10,
    "BONUS_TURKEY": 2
  },
  "pending_by_reason_top": [
    [
      "Public CWMU big-game permits use the Utah bonus model and only promote rows with proven public-draw source data, valid quota, and modeled bonus probabilities.",
      383
    ],
    [
      "General-season buck deer uses a preference-point model and only promotes rows with valid source history, quota, and modeled preference probabilities.",
      132
    ],
    [
      "Public limited-entry and restricted-pursuit bear rows use the Utah bonus model only when the source history proves real draw status, valid quota, and modeled bonus probabilities.",
      83
    ],
    [
      "Antlerless moose uses the Utah bonus model and only promotes rows with valid source history, forecast quota, and modeled bonus probabilities.",
      10
    ],
    [
      "Draw-only youth elk stays in scope but remains pending until current-year quota and mechanics are source-proven.",
      2
    ],
    [
      "Limited-entry turkey uses the Utah bonus model and only promotes rows with proven limited-entry public-draw source data, valid quota, and modeled bonus probabilities.",
      2
    ]
  ],
  "pending_by_year": {
    "2026": 612
  },
  "pending_by_target_scope": {
    "TARGET": 612
  },
  "pending_unique_hunt_codes": 396,
  "pending_samples": [
    {
      "hunt_code": "BR1015",
      "hunt_name": "Book Cliffs",
      "species": "Black Bear",
      "hunt_type": "Restricted Pursuit - Spring",
      "residency": "Resident",
      "points": "",
      "draw_pool": "standard",
      "draw_system_type": "BEAR_DRAW",
      "algorithm_status": "IN_SCOPE_MODEL_PENDING",
      "reason": "Public limited-entry and restricted-pursuit bear rows use the Utah bonus model only when the source history proves real draw status, valid quota, and modeled bonus probabilities.",
      "model_strategy": "bear_bonus_phase8",
      "preference_model_valid": "",
      "p_draw": "",
      "p_draw_pct": "",
      "p_preference_draw": "",
      "quota_2026_total": ""
    },
    {
      "hunt_code": "BR1016",
      "hunt_name": "San Juan",
      "species": "Black Bear",
      "hunt_type": "Restricted Pursuit - Spring",
      "residency": "Resident",
      "points": "",
      "draw_pool": "standard",
      "draw_system_type": "BEAR_DRAW",
      "algorithm_status": "IN_SCOPE_MODEL_PENDING",
      "reason": "Public limited-entry and restricted-pursuit bear rows use the Utah bonus model only when the source history proves real draw status, valid quota, and modeled bonus probabilities.",
      "model_strategy": "bear_bonus_phase8",
      "preference_model_valid": "",
      "p_draw": "",
      "p_draw_pct": "",
      "p_preference_draw": "",
      "quota_2026_total": ""
    },
    {
      "hunt_code": "BR1017",
      "hunt_name": "La Sal",
      "species": "Black Bear",
      "hunt_type": "Restricted Pursuit - Spring",
      "residency": "Resident",
      "points": "",
      "draw_pool": "standard",
      "draw_system_type": "BEAR_DRAW",
      "algorithm_status": "IN_SCOPE_MODEL_PENDING",
      "reason": "Public limited-entry and restricted-pursuit bear rows use the Utah bonus model only when the source history proves real draw status, valid quota, and modeled bonus probabilities.",
      "model_strategy": "bear_bonus_phase8",
      "preference_model_valid": "",
      "p_draw": "",
      "p_draw_pct": "",
      "p_preference_draw": "",
      "quota_2026_total": ""
    },
    {
      "hunt_code": "BR7005",
      "hunt_name": "Nebo",
      "species": "Black Bear",
      "hunt_type": "Limited Entry - Spring",
      "residency": "Nonresident",
      "points": "",
      "draw_pool": "standard",
      "draw_system_type": "BEAR_DRAW",
      "algorithm_status": "IN_SCOPE_MODEL_PENDING",
      "reason": "Public limited-entry and restricted-pursuit bear rows use the Utah bonus model only when the source history proves real draw status, valid quota, and modeled bonus probabilities.",
      "model_strategy": "bear_bonus_phase8",
      "preference_model_valid": "",
      "p_draw": "",
      "p_draw_pct": "",
      "p_preference_draw": "",
      "quota_2026_total": ""
    },
    {
      "hunt_code": "BR7007",
      "hunt_name": "Fillmore Pahvant",
      "species": "Black Bear",
      "hunt_type": "Limited Entry - Spring",
      "residency": "Nonresident",
      "points": "",
      "draw_pool": "standard",
      "draw_system_type": "BEAR_DRAW",
      "algorithm_status": "IN_SCOPE_MODEL_PENDING",
      "reason": "Public limited-entry and restricted-pursuit bear rows use the Utah bonus model only when the source history proves real draw status, valid quota, and modeled bonus probabilities.",
      "model_strategy": "bear_bonus_phase8",
      "preference_model_valid": "",
      "p_draw": "",
      "p_draw_pct": "",
      "p_preference_draw": "",
      "quota_2026_total": ""
    },
    {
      "hunt_code": "BR7008",
      "hunt_name": "La Sal",
      "species": "Black Bear",
      "hunt_type": "Limited Entry - Spring",
      "residency": "Nonresident",
      "points": "",
      "draw_pool": "standard",
      "draw_system_type": "BEAR_DRAW",
      "algorithm_status": "IN_SCOPE_MODEL_PENDING",
      "reason": "Public limited-entry and restricted-pursuit bear rows use the Utah bonus model only when the source history proves real draw status, valid quota, and modeled bonus probabilities.",
      "model_strategy": "bear_bonus_phase8",
      "preference_model_valid": "",
      "p_draw": "",
      "p_draw_pct": "",
      "p_preference_draw": "",
      "quota_2026_total": ""
    },
    {
      "hunt_code": "BR7008",
      "hunt_name": "La Sal",
      "species": "Black Bear",
      "hunt_type": "Limited Entry - Spring",
      "residency": "Resident",
      "points": "",
      "draw_pool": "standard",
      "draw_system_type": "BEAR_DRAW",
      "algorithm_status": "IN_SCOPE_MODEL_PENDING",
      "reason": "Public limited-entry and restricted-pursuit bear rows use the Utah bonus model only when the source history proves real draw status, valid quota, and modeled bonus probabilities.",
      "model_strategy": "bear_bonus_phase8",
      "preference_model_valid": "",
      "p_draw": "",
      "p_draw_pct": "",
      "p_preference_draw": "",
      "quota_2026_total": ""
    },
    {
      "hunt_code": "BR7009",
      "hunt_name": "Mt Dutton",
      "species": "Black Bear",
      "hunt_type": "Limited Entry - Spring",
      "residency": "Nonresident",
      "points": "",
      "draw_pool": "standard",
      "draw_system_type": "BEAR_DRAW",
      "algorithm_status": "IN_SCOPE_MODEL_PENDING",
      "reason": "Public limited-entry and restricted-pursuit bear rows use the Utah bonus model only when the source history proves real draw status, valid quota, and modeled bonus probabilities.",
      "model_strategy": "bear_bonus_phase8",
      "preference_model_valid": "",
      "p_draw": "",
      "p_draw_pct": "",
      "p_preference_draw": "",
      "quota_2026_total": ""
    },
    {
      "hunt_code": "BR7010",
      "hunt_name": "Panguitch Lake/Zion",
      "species": "Black Bear",
      "hunt_type": "Limited Entry - Spring",
      "residency": "Nonresident",
      "points": "",
      "draw_pool": "standard",
      "draw_system_type": "BEAR_DRAW",
      "algorithm_status": "IN_SCOPE_MODEL_PENDING",
      "reason": "Public limited-entry and restricted-pursuit bear rows use the Utah bonus model only when the source history proves real draw status, valid quota, and modeled bonus probabilities.",
      "model_strategy": "bear_bonus_phase8",
      "preference_model_valid": "",
      "p_draw": "",
      "p_draw_pct": "",
      "p_preference_draw": "",
      "quota_2026_total": ""
    },
    {
      "hunt_code": "BR7011",
      "hunt_name": "Paunsaugunt",
      "species": "Black Bear",
      "hunt_type": "Limited Entry - Spring",
      "residency": "Nonresident",
      "points": "",
      "draw_pool": "standard",
      "draw_system_type": "BEAR_DRAW",
      "algorithm_status": "IN_SCOPE_MODEL_PENDING",
      "reason": "Public limited-entry and restricted-pursuit bear rows use the Utah bonus model only when the source history proves real draw status, valid quota, and modeled bonus probabilities.",
      "model_strategy": "bear_bonus_phase8",
      "preference_model_valid": "",
      "p_draw": "",
      "p_draw_pct": "",
      "p_preference_draw": "",
      "quota_2026_total": ""
    },
    {
      "hunt_code": "BR7013",
      "hunt_name": "Fishlake/Thousand Lakes",
      "species": "Black Bear",
      "hunt_type": "Limited Entry - Spring",
      "residency": "Nonresident",
      "points": "",
      "draw_pool": "standard",
      "draw_system_type": "BEAR_DRAW",
      "algorithm_status": "IN_SCOPE_MODEL_PENDING",
      "reason": "Public limited-entry and restricted-pursuit bear rows use the Utah bonus model only when the source history proves real draw status, valid quota, and modeled bonus probabilities.",
      "model_strategy": "bear_bonus_phase8",
      "preference_model_valid": "",
      "p_draw": "",
      "p_draw_pct": "",
      "p_preference_draw": "",
      "quota_2026_total": ""
    },
    {
      "hunt_code": "BR7015",
      "hunt_name": "Diamond Mtn/Vernal/Bonanza",
      "species": "Black Bear",
      "hunt_type": "Limited Entry - Spring",
      "residency": "Nonresident",
      "points": "",
      "draw_pool": "standard",
      "draw_system_type": "BEAR_DRAW",
      "algorithm_status": "IN_SCOPE_MODEL_PENDING",
      "reason": "Public limited-entry and restricted-pursuit bear rows use the Utah bonus model only when the source history proves real draw status, valid quota, and modeled bonus probabilities.",
      "model_strategy": "bear_bonus_phase8",
      "preference_model_valid": "",
      "p_draw": "",
      "p_draw_pct": "",
      "p_preference_draw": "",
      "quota_2026_total": ""
    },
    {
      "hunt_code": "BR7017",
      "hunt_name": "Cache/Ogden",
      "species": "Black Bear",
      "hunt_type": "Limited Entry - Spring",
      "residency": "Nonresident",
      "points": "",
      "draw_pool": "standard",
      "draw_system_type": "BEAR_DRAW",
      "algorithm_status": "IN_SCOPE_MODEL_PENDING",
      "reason": "Public limited-entry and restricted-pursuit bear rows use the Utah bonus model only when the source history proves real draw status, valid quota, and modeled bonus probabilities.",
      "model_strategy": "bear_bonus_phase8",
      "preference_model_valid": "",
      "p_draw": "",
      "p_draw_pct": "",
      "p_preference_draw": "",
      "quota_2026_total": ""
    },
    {
      "hunt_code": "BR7018",
      "hunt_name": "Kamas/North Slope Summit",
      "species": "Black Bear",
      "hunt_type": "Limited Entry - Spring",
      "residency": "Nonresident",
      "points": "",
      "draw_pool": "standard",
      "draw_system_type": "BEAR_DRAW",
      "algorithm_status": "IN_SCOPE_MODEL_PENDING",
      "reason": "Public limited-entry and restricted-pursuit bear rows use the Utah bonus model only when the source history proves real draw status, valid quota, and modeled bonus probabilities.",
      "model_strategy": "bear_bonus_phase8",
      "preference_model_valid": "",
      "p_draw": "",
      "p_draw_pct": "",
      "p_preference_draw": "",
      "quota_2026_total": ""
    },
    {
      "hunt_code": "BR7019",
      "hunt_name": "Chalk Creek/East Canyon/Morgan-South Rich",
      "species": "Black Bear",
      "hunt_type": "Limited Entry - Spring",
      "residency": "Nonresident",
      "points": "",
      "draw_pool": "standard",
      "draw_system_type": "BEAR_DRAW",
      "algorithm_status": "IN_SCOPE_MODEL_PENDING",
      "reason": "Public limited-entry and restricted-pursuit bear rows use the Utah bonus model only when the source history proves real draw status, valid quota, and modeled bonus probabilities.",
      "model_strategy": "bear_bonus_phase8",
      "preference_model_valid": "",
      "p_draw": "",
      "p_draw_pct": "",
      "p_preference_draw": "",
      "quota_2026_total": ""
    },
    {
      "hunt_code": "BR7019",
      "hunt_name": "Chalk Creek/East Canyon/Morgan-South Rich",
      "species": "Black Bear",
      "hunt_type": "Limited Entry - Spring",
      "residency": "Resident",
      "points": "",
      "draw_pool": "standard",
      "draw_system_type": "BEAR_DRAW",
      "algorithm_status": "IN_SCOPE_MODEL_PENDING",
      "reason": "Public limited-entry and restricted-pursuit bear rows use the Utah bonus model only when the source history proves real draw status, valid quota, and modeled bonus probabilities.",
      "model_strategy": "bear_bonus_phase8",
      "preference_model_valid": "",
      "p_draw": "",
      "p_draw_pct": "",
      "p_preference_draw": "",
      "quota_2026_total": ""
    },
    {
      "hunt_code": "BR7020",
      "hunt_name": "Monroe",
      "species": "Black Bear",
      "hunt_type": "Limited Entry - Spring",
      "residency": "Nonresident",
      "points": "",
      "draw_pool": "standard",
      "draw_system_type": "BEAR_DRAW",
      "algorithm_status": "IN_SCOPE_MODEL_PENDING",
      "reason": "Public limited-entry and restricted-pursuit bear rows use the Utah bonus model only when the source history proves real draw status, valid quota, and modeled bonus probabilities.",
      "model_strategy": "bear_bonus_phase8",
      "preference_model_valid": "",
      "p_draw": "",
      "p_draw_pct": "",
      "p_preference_draw": "",
      "quota_2026_total": ""
    },
    {
      "hunt_code": "BR7021",
      "hunt_name": "Dolores Triangle",
      "species": "Black Bear",
      "hunt_type": "Limited Entry - Spring",
      "residency": "Nonresident",
      "points": "",
      "draw_pool": "standard",
      "draw_system_type": "BEAR_DRAW",
      "algorithm_status": "IN_SCOPE_MODEL_PENDING",
      "reason": "Public limited-entry and restricted-pursuit bear rows use the Utah bonus model only when the source history proves real draw status, valid quota, and modeled bonus probabilities.",
      "model_strategy": "bear_bonus_phase8",
      "preference_model_valid": "",
      "p_draw": "",
      "p_draw_pct": "",
      "p_preference_draw": "",
      "quota_2026_total": ""
    },
    {
      "hunt_code": "BR7021",
      "hunt_name": "Dolores Triangle",
      "species": "Black Bear",
      "hunt_type": "Limited Entry - Spring",
      "residency": "Resident",
      "points": "",
      "draw_pool": "standard",
      "draw_system_type": "BEAR_DRAW",
      "algorithm_status": "IN_SCOPE_MODEL_PENDING",
      "reason": "Public limited-entry and restricted-pursuit bear rows use the Utah bonus model only when the source history proves real draw status, valid quota, and modeled bonus probabilities.",
      "model_strategy": "bear_bonus_phase8",
      "preference_model_valid": "",
      "p_draw": "",
      "p_draw_pct": "",
      "p_preference_draw": "",
      "quota_2026_total": ""
    },
    {
      "hunt_code": "BR7022",
      "hunt_name": "La Sal Mtns",
      "species": "Black Bear",
      "hunt_type": "Limited Entry - Spring",
      "residency": "Nonresident",
      "points": "",
      "draw_pool": "standard",
      "draw_system_type": "BEAR_DRAW",
      "algorithm_status": "IN_SCOPE_MODEL_PENDING",
      "reason": "Public limited-entry and restricted-pursuit bear rows use the Utah bonus model only when the source history proves real draw status, valid quota, and modeled bonus probabilities.",
      "model_strategy": "bear_bonus_phase8",
      "preference_model_valid": "",
      "p_draw": "",
      "p_draw_pct": "",
      "p_preference_draw": "",
      "quota_2026_total": ""
    },
    {
      "hunt_code": "BR7022",
      "hunt_name": "La Sal Mtns",
      "species": "Black Bear",
      "hunt_type": "Limited Entry - Spring",
      "residency": "Resident",
      "points": "",
      "draw_pool": "standard",
      "draw_system_type": "BEAR_DRAW",
      "algorithm_status": "IN_SCOPE_MODEL_PENDING",
      "reason": "Public limited-entry and restricted-pursuit bear rows use the Utah bonus model only when the source history proves real draw status, valid quota, and modeled bonus probabilities.",
      "model_strategy": "bear_bonus_phase8",
      "preference_model_valid": "",
      "p_draw": "",
      "p_draw_pct": "",
      "p_preference_draw": "",
      "quota_2026_total": ""
    },
    {
      "hunt_code": "BR7102",
      "hunt_name": "Book Cliffs Little Creek Roadless",
      "species": "Black Bear",
      "hunt_type": "Limited Entry - Summer",
      "residency": "Nonresident",
      "points": "",
      "draw_pool": "standard",
      "draw_system_type": "BEAR_DRAW",
      "algorithm_status": "IN_SCOPE_MODEL_PENDING",
      "reason": "Public limited-entry and restricted-pursuit bear rows use the Utah bonus model only when the source history proves real draw status, valid quota, and modeled bonus probabilities.",
      "model_strategy": "bear_bonus_phase8",
      "preference_model_valid": "",
      "p_draw": "",
      "p_draw_pct": "",
      "p_preference_draw": "",
      "quota_2026_total": ""
    },
    {
      "hunt_code": "BR7106",
      "hunt_name": "Nebo",
      "species": "Black Bear",
      "hunt_type": "Limited Entry - Summer",
      "residency": "Nonresident",
      "points": "",
      "draw_pool": "standard",
      "draw_system_type": "BEAR_DRAW",
      "algorithm_status": "IN_SCOPE_MODEL_PENDING",
      "reason": "Public limited-entry and restricted-pursuit bear rows use the Utah bonus model only when the source history proves real draw status, valid quota, and modeled bonus probabilities.",
      "model_strategy": "bear_bonus_phase8",
      "preference_model_valid": "",
      "p_draw": "",
      "p_draw_pct": "",
      "p_preference_draw": "",
      "quota_2026_total": ""
    },
    {
      "hunt_code": "BR7108",
      "hunt_name": "La Sal",
      "species": "Black Bear",
      "hunt_type": "Limited Entry - Summer",
      "residency": "Nonresident",
      "points": "",
      "draw_pool": "standard",
      "draw_system_type": "BEAR_DRAW",
      "algorithm_status": "IN_SCOPE_MODEL_PENDING",
      "reason": "Public limited-entry and restricted-pursuit bear rows use the Utah bonus model only when the source history proves real draw status, valid quota, and modeled bonus probabilities.",
      "model_strategy": "bear_bonus_phase8",
      "preference_model_valid": "",
      "p_draw": "",
      "p_draw_pct": "",
      "p_preference_draw": "",
      "quota_2026_total": ""
    },
    {
      "hunt_code": "BR7108",
      "hunt_name": "La Sal",
      "species": "Black Bear",
      "hunt_type": "Limited Entry - Summer",
      "residency": "Resident",
      "points": "",
      "draw_pool": "standard",
      "draw_system_type": "BEAR_DRAW",
      "algorithm_status": "IN_SCOPE_MODEL_PENDING",
      "reason": "Public limited-entry and restricted-pursuit bear rows use the Utah bonus model only when the source history proves real draw status, valid quota, and modeled bonus probabilities.",
      "model_strategy": "bear_bonus_phase8",
      "preference_model_valid": "",
      "p_draw": "",
      "p_draw_pct": "",
      "p_preference_draw": "",
      "quota_2026_total": ""
    },
    {
      "hunt_code": "BR7109",
      "hunt_name": "Mt Dutton",
      "species": "Black Bear",
      "hunt_type": "Limited Entry - Summer",
      "residency": "Nonresident",
      "points": "",
      "draw_pool": "standard",
      "draw_system_type": "BEAR_DRAW",
      "algorithm_status": "IN_SCOPE_MODEL_PENDING",
      "reason": "Public limited-entry and restricted-pursuit bear rows use the Utah bonus model only when the source history proves real draw status, valid quota, and modeled bonus probabilities.",
      "model_strategy": "bear_bonus_phase8",
      "preference_model_valid": "",
      "p_draw": "",
      "p_draw_pct": "",
      "p_preference_draw": "",
      "quota_2026_total": ""
    },
    {
      "hunt_code": "BR7110",
      "hunt_name": "Nine Mile",
      "species": "Black Bear",
      "hunt_type": "Limited Entry - Summer",
      "residency": "Nonresident",
      "points": "",
      "draw_pool": "standard",
      "draw_system_type": "BEAR_DRAW",
      "algorithm_status": "IN_SCOPE_MODEL_PENDING",
      "reason": "Public limited-entry and restricted-pursuit bear rows use the Utah bonus model only when the source history proves real draw status, valid quota, and modeled bonus probabilities.",
      "model_strategy": "bear_bonus_phase8",
      "preference_model_valid": "",
      "p_draw": "",
      "p_draw_pct": "",
      "p_preference_draw": "",
      "quota_2026_total": ""
    },
    {
      "hunt_code": "BR7111",
      "hunt_name": "North Slope Three Corners/West Daggett",
      "species": "Black Bear",
      "hunt_type": "Limited Entry - Summer",
      "residency": "Nonresident",
      "points": "",
      "draw_pool": "standard",
      "draw_system_type": "BEAR_DRAW",
      "algorithm_status": "IN_SCOPE_MODEL_PENDING",
      "reason": "Public limited-entry and restricted-pursuit bear rows use the Utah bonus model only when the source history proves real draw status, valid quota, and modeled bonus probabilities.",
      "model_strategy": "bear_bonus_phase8",
      "preference_model_valid": "",
      "p_draw": "",
      "p_draw_pct": "",
      "p_preference_draw": "",
      "quota_2026_total": ""
    },
    {
      "hunt_code": "BR7112",
      "hunt_name": "Panguitch Lake/Zion",
      "species": "Black Bear",
      "hunt_type": "Limited Entry - Summer",
      "residency": "Nonresident",
      "points": "",
      "draw_pool": "standard",
      "draw_system_type": "BEAR_DRAW",
      "algorithm_status": "IN_SCOPE_MODEL_PENDING",
      "reason": "Public limited-entry and restricted-pursuit bear rows use the Utah bonus model only when the source history proves real draw status, valid quota, and modeled bonus probabilities.",
      "model_strategy": "bear_bonus_phase8",
      "preference_model_valid": "",
      "p_draw": "",
      "p_draw_pct": "",
      "p_preference_draw": "",
      "quota_2026_total": ""
    },
    {
      "hunt_code": "BR7113",
      "hunt_name": "Paunsaugunt",
      "species": "Black Bear",
      "hunt_type": "Limited Entry - Summer",
      "residency": "Nonresident",
      "points": "",
      "draw_pool": "standard",
      "draw_system_type": "BEAR_DRAW",
      "algorithm_status": "IN_SCOPE_MODEL_PENDING",
      "reason": "Public limited-entry and restricted-pursuit bear rows use the Utah bonus model only when the source history proves real draw status, valid quota, and modeled bonus probabilities.",
      "model_strategy": "bear_bonus_phase8",
      "preference_model_valid": "",
      "p_draw": "",
      "p_draw_pct": "",
      "p_preference_draw": "",
      "quota_2026_total": ""
    },
    {
      "hunt_code": "BR7115",
      "hunt_name": "Fishlake/Thousand Lakes",
      "species": "Black Bear",
      "hunt_type": "Limited Entry - Summer",
      "residency": "Nonresident",
      "points": "",
      "draw_pool": "standard",
      "draw_system_type": "BEAR_DRAW",
      "algorithm_status": "IN_SCOPE_MODEL_PENDING",
      "reason": "Public limited-entry and restricted-pursuit bear rows use the Utah bonus model only when the source history proves real draw status, valid quota, and modeled bonus probabilities.",
      "model_strategy": "bear_bonus_phase8",
      "preference_model_valid": "",
      "p_draw": "",
      "p_draw_pct": "",
      "p_preference_draw": "",
      "quota_2026_total": ""
    },
    {
      "hunt_code": "BR7117",
      "hunt_name": "Diamond Mtn/Vernal/Bonanza",
      "species": "Black Bear",
      "hunt_type": "Limited Entry - Summer",
      "residency": "Nonresident",
      "points": "",
      "draw_pool": "standard",
      "draw_system_type": "BEAR_DRAW",
      "algorithm_status": "IN_SCOPE_MODEL_PENDING",
      "reason": "Public limited-entry and restricted-pursuit bear rows use the Utah bonus model only when the source history proves real draw status, valid quota, and modeled bonus probabilities.",
      "model_strategy": "bear_bonus_phase8",
      "preference_model_valid": "",
      "p_draw": "",
      "p_draw_pct": "",
      "p_preference_draw": "",
      "quota_2026_total": ""
    },
    {
      "hunt_code": "BR7118",
      "hunt_name": "Yellowstone",
      "species": "Black Bear",
      "hunt_type": "Limited Entry - Summer",
      "residency": "Nonresident",
      "points": "",
      "draw_pool": "standard",
      "draw_system_type": "BEAR_DRAW",
      "algorithm_status": "IN_SCOPE_MODEL_PENDING",
      "reason": "Public limited-entry and restricted-pursuit bear rows use the Utah bonus model only when the source history proves real draw status, valid quota, and modeled bonus probabilities.",
      "model_strategy": "bear_bonus_phase8",
      "preference_model_valid": "",
      "p_draw": "",
      "p_draw_pct": "",
      "p_preference_draw": "",
      "quota_2026_total": ""
    },
    {
      "hunt_code": "BR7119",
      "hunt_name": "Wasatch Mtns Avintaquin/Currant Creek",
      "species": "Black Bear",
      "hunt_type": "Limited Entry - Summer",
      "residency": "Nonresident",
      "points": "",
      "draw_pool": "standard",
      "draw_system_type": "BEAR_DRAW",
      "algorithm_status": "IN_SCOPE_MODEL_PENDING",
      "reason": "Public limited-entry and restricted-pursuit bear rows use the Utah bonus model only when the source history proves real draw status, valid quota, and modeled bonus probabilities.",
      "model_strategy": "bear_bonus_phase8",
      "preference_model_valid": "",
      "p_draw": "",
      "p_draw_pct": "",
      "p_preference_draw": "",
      "quota_2026_total": ""
    },
    {
      "hunt_code": "BR7121",
      "hunt_name": "Cache/Ogden",
      "species": "Black Bear",
      "hunt_type": "Limited Entry - Summer",
      "residency": "Nonresident",
      "points": "",
      "draw_pool": "standard",
      "draw_system_type": "BEAR_DRAW",
      "algorithm_status": "IN_SCOPE_MODEL_PENDING",
      "reason": "Public limited-entry and restricted-pursuit bear rows use the Utah bonus model only when the source history proves real draw status, valid quota, and modeled bonus probabilities.",
      "model_strategy": "bear_bonus_phase8",
      "preference_model_valid": "",
      "p_draw": "",
      "p_draw_pct": "",
      "p_preference_draw": "",
      "quota_2026_total": ""
    },
    {
      "hunt_code": "BR7122",
      "hunt_name": "Chalk Creek/East Canyon/Morgan-South Rich",
      "species": "Black Bear",
      "hunt_type": "Limited Entry - Summer",
      "residency": "Nonresident",
      "points": "",
      "draw_pool": "standard",
      "draw_system_type": "BEAR_DRAW",
      "algorithm_status": "IN_SCOPE_MODEL_PENDING",
      "reason": "Public limited-entry and restricted-pursuit bear rows use the Utah bonus model only when the source history proves real draw status, valid quota, and modeled bonus probabilities.",
      "model_strategy": "bear_bonus_phase8",
      "preference_model_valid": "",
      "p_draw": "",
      "p_draw_pct": "",
      "p_preference_draw": "",
      "quota_2026_total": ""
    },
    {
      "hunt_code": "BR7123",
      "hunt_name": "Kamas/North Slope Summit",
      "species": "Black Bear",
      "hunt_type": "Limited Entry - Summer",
      "residency": "Nonresident",
      "points": "",
      "draw_pool": "standard",
      "draw_system_type": "BEAR_DRAW",
      "algorithm_status": "IN_SCOPE_MODEL_PENDING",
      "reason": "Public limited-entry and restricted-pursuit bear rows use the Utah bonus model only when the source history proves real draw status, valid quota, and modeled bonus probabilities.",
      "model_strategy": "bear_bonus_phase8",
      "preference_model_valid": "",
      "p_draw": "",
      "p_draw_pct": "",
      "p_preference_draw": "",
      "quota_2026_total": ""
    },
    {
      "hunt_code": "BR7124",
      "hunt_name": "Fillmore Pahvant",
      "species": "Black Bear",
      "hunt_type": "Limited Entry - Summer",
      "residency": "Nonresident",
      "points": "",
      "draw_pool": "standard",
      "draw_system_type": "BEAR_DRAW",
      "algorithm_status": "IN_SCOPE_MODEL_PENDING",
      "reason": "Public limited-entry and restricted-pursuit bear rows use the Utah bonus model only when the source history proves real draw status, valid quota, and modeled bonus probabilities.",
      "model_strategy": "bear_bonus_phase8",
      "preference_model_valid": "",
      "p_draw": "",
      "p_draw_pct": "",
      "p_preference_draw": "",
      "quota_2026_total": ""
    },
    {
      "hunt_code": "BR7125",
      "hunt_name": "Monroe",
      "species": "Black Bear",
      "hunt_type": "Limited Entry - Summer",
      "residency": "Nonresident",
      "points": "",
      "draw_pool": "standard",
      "draw_system_type": "BEAR_DRAW",
      "algorithm_status": "IN_SCOPE_MODEL_PENDING",
      "reason": "Public limited-entry and restricted-pursuit bear rows use the Utah bonus model only when the source history proves real draw status, valid quota, and modeled bonus probabilities.",
      "model_strategy": "bear_bonus_phase8",
      "preference_model_valid": "",
      "p_draw": "",
      "p_draw_pct": "",
      "p_preference_draw": "",
      "quota_2026_total": ""
    },
    {
      "hunt_code": "BR7126",
      "hunt_name": "Dolores Triangle",
      "species": "Black Bear",
      "hunt_type": "Limited Entry - Summer",
      "residency": "Nonresident",
      "points": "",
      "draw_pool": "standard",
      "draw_system_type": "BEAR_DRAW",
      "algorithm_status": "IN_SCOPE_MODEL_PENDING",
      "reason": "Public limited-entry and restricted-pursuit bear rows use the Utah bonus model only when the source history proves real draw status, valid quota, and modeled bonus probabilities.",
      "model_strategy": "bear_bonus_phase8",
      "preference_model_valid": "",
      "p_draw": "",
      "p_draw_pct": "",
      "p_preference_draw": "",
      "quota_2026_total": ""
    },
    {
      "hunt_code": "BR7126",
      "hunt_name": "Dolores Triangle",
      "species": "Black Bear",
      "hunt_type": "Limited Entry - Summer",
      "residency": "Resident",
      "points": "",
      "draw_pool": "standard",
      "draw_system_type": "BEAR_DRAW",
      "algorithm_status": "IN_SCOPE_MODEL_PENDING",
      "reason": "Public limited-entry and restricted-pursuit bear rows use the Utah bonus model only when the source history proves real draw status, valid quota, and modeled bonus probabilities.",
      "model_strategy": "bear_bonus_phase8",
      "preference_model_valid": "",
      "p_draw": "",
      "p_draw_pct": "",
      "p_preference_draw": "",
      "quota_2026_total": ""
    },
    {
      "hunt_code": "BR7127",
      "hunt_name": "La Sal Mtns",
      "species": "Black Bear",
      "hunt_type": "Limited Entry - Summer",
      "residency": "Nonresident",
      "points": "",
      "draw_pool": "standard",
      "draw_system_type": "BEAR_DRAW",
      "algorithm_status": "IN_SCOPE_MODEL_PENDING",
      "reason": "Public limited-entry and restricted-pursuit bear rows use the Utah bonus model only when the source history proves real draw status, valid quota, and modeled bonus probabilities.",
      "model_strategy": "bear_bonus_phase8",
      "preference_model_valid": "",
      "p_draw": "",
      "p_draw_pct": "",
      "p_preference_draw": "",
      "quota_2026_total": ""
    },
    {
      "hunt_code": "BR7127",
      "hunt_name": "La Sal Mtns",
      "species": "Black Bear",
      "hunt_type": "Limited Entry - Summer",
      "residency": "Resident",
      "points": "",
      "draw_pool": "standard",
      "draw_system_type": "BEAR_DRAW",
      "algorithm_status": "IN_SCOPE_MODEL_PENDING",
      "reason": "Public limited-entry and restricted-pursuit bear rows use the Utah bonus model only when the source history proves real draw status, valid quota, and modeled bonus probabilities.",
      "model_strategy": "bear_bonus_phase8",
      "preference_model_valid": "",
      "p_draw": "",
      "p_draw_pct": "",
      "p_preference_draw": "",
      "quota_2026_total": ""
    },
    {
      "hunt_code": "BR7205",
      "hunt_name": "Nebo",
      "species": "Black Bear",
      "hunt_type": "Limited Entry - Fall",
      "residency": "Nonresident",
      "points": "",
      "draw_pool": "standard",
      "draw_system_type": "BEAR_DRAW",
      "algorithm_status": "IN_SCOPE_MODEL_PENDING",
      "reason": "Public limited-entry and restricted-pursuit bear rows use the Utah bonus model only when the source history proves real draw status, valid quota, and modeled bonus probabilities.",
      "model_strategy": "bear_bonus_phase8",
      "preference_model_valid": "",
      "p_draw": "",
      "p_draw_pct": "",
      "p_preference_draw": "",
      "quota_2026_total": ""
    },
    {
      "hunt_code": "BR7207",
      "hunt_name": "Fillmore Pahvant",
      "species": "Black Bear",
      "hunt_type": "Limited Entry - Fall",
      "residency": "Nonresident",
      "points": "",
      "draw_pool": "standard",
      "draw_system_type": "BEAR_DRAW",
      "algorithm_status": "IN_SCOPE_MODEL_PENDING",
      "reason": "Public limited-entry and restricted-pursuit bear rows use the Utah bonus model only when the source history proves real draw status, valid quota, and modeled bonus probabilities.",
      "model_strategy": "bear_bonus_phase8",
      "preference_model_valid": "",
      "p_draw": "",
      "p_draw_pct": "",
      "p_preference_draw": "",
      "quota_2026_total": ""
    },
    {
      "hunt_code": "BR7208",
      "hunt_name": "La Sal",
      "species": "Black Bear",
      "hunt_type": "Limited Entry - Fall",
      "residency": "Nonresident",
      "points": "",
      "draw_pool": "standard",
      "draw_system_type": "BEAR_DRAW",
      "algorithm_status": "IN_SCOPE_MODEL_PENDING",
      "reason": "Public limited-entry and restricted-pursuit bear rows use the Utah bonus model only when the source history proves real draw status, valid quota, and modeled bonus probabilities.",
      "model_strategy": "bear_bonus_phase8",
      "preference_model_valid": "",
      "p_draw": "",
      "p_draw_pct": "",
      "p_preference_draw": "",
      "quota_2026_total": ""
    },
    {
      "hunt_code": "BR7208",
      "hunt_name": "La Sal",
      "species": "Black Bear",
      "hunt_type": "Limited Entry - Fall",
      "residency": "Resident",
      "points": "",
      "draw_pool": "standard",
      "draw_system_type": "BEAR_DRAW",
      "algorithm_status": "IN_SCOPE_MODEL_PENDING",
      "reason": "Public limited-entry and restricted-pursuit bear rows use the Utah bonus model only when the source history proves real draw status, valid quota, and modeled bonus probabilities.",
      "model_strategy": "bear_bonus_phase8",
      "preference_model_valid": "",
      "p_draw": "",
      "p_draw_pct": "",
      "p_preference_draw": "",
      "quota_2026_total": ""
    },
    {
      "hunt_code": "BR7210",
      "hunt_name": "Mt Dutton",
      "species": "Black Bear",
      "hunt_type": "Limited Entry - Fall",
      "residency": "Nonresident",
      "points": "",
      "draw_pool": "standard",
      "draw_system_type": "BEAR_DRAW",
      "algorithm_status": "IN_SCOPE_MODEL_PENDING",
      "reason": "Public limited-entry and restricted-pursuit bear rows use the Utah bonus model only when the source history proves real draw status, valid quota, and modeled bonus probabilities.",
      "model_strategy": "bear_bonus_phase8",
      "preference_model_valid": "",
      "p_draw": "",
      "p_draw_pct": "",
      "p_preference_draw": "",
      "quota_2026_total": ""
    },
    {
      "hunt_code": "BR7210",
      "hunt_name": "Mt Dutton",
      "species": "Black Bear",
      "hunt_type": "Limited Entry - Fall",
      "residency": "Resident",
      "points": "",
      "draw_pool": "standard",
      "draw_system_type": "BEAR_DRAW",
      "algorithm_status": "IN_SCOPE_MODEL_PENDING",
      "reason": "Public limited-entry and restricted-pursuit bear rows use the Utah bonus model only when the source history proves real draw status, valid quota, and modeled bonus probabilities.",
      "model_strategy": "bear_bonus_phase8",
      "preference_model_valid": "",
      "p_draw": "",
      "p_draw_pct": "",
      "p_preference_draw": "",
      "quota_2026_total": ""
    },
    {
      "hunt_code": "BR7211",
      "hunt_name": "Nine Mile",
      "species": "Black Bear",
      "hunt_type": "Limited Entry - Fall",
      "residency": "Nonresident",
      "points": "",
      "draw_pool": "standard",
      "draw_system_type": "BEAR_DRAW",
      "algorithm_status": "IN_SCOPE_MODEL_PENDING",
      "reason": "Public limited-entry and restricted-pursuit bear rows use the Utah bonus model only when the source history proves real draw status, valid quota, and modeled bonus probabilities.",
      "model_strategy": "bear_bonus_phase8",
      "preference_model_valid": "",
      "p_draw": "",
      "p_draw_pct": "",
      "p_preference_draw": "",
      "quota_2026_total": ""
    },
    {
      "hunt_code": "BR7212",
      "hunt_name": "North Slope Three Corners/West Daggett",
      "species": "Black Bear",
      "hunt_type": "Limited Entry - Fall",
      "residency": "Nonresident",
      "points": "",
      "draw_pool": "standard",
      "draw_system_type": "BEAR_DRAW",
      "algorithm_status": "IN_SCOPE_MODEL_PENDING",
      "reason": "Public limited-entry and restricted-pursuit bear rows use the Utah bonus model only when the source history proves real draw status, valid quota, and modeled bonus probabilities.",
      "model_strategy": "bear_bonus_phase8",
      "preference_model_valid": "",
      "p_draw": "",
      "p_draw_pct": "",
      "p_preference_draw": "",
      "quota_2026_total": ""
    },
    {
      "hunt_code": "BR7213",
      "hunt_name": "Panguitch Lake/Zion",
      "species": "Black Bear",
      "hunt_type": "Limited Entry - Fall",
      "residency": "Nonresident",
      "points": "",
      "draw_pool": "standard",
      "draw_system_type": "BEAR_DRAW",
      "algorithm_status": "IN_SCOPE_MODEL_PENDING",
      "reason": "Public limited-entry and restricted-pursuit bear rows use the Utah bonus model only when the source history proves real draw status, valid quota, and modeled bonus probabilities.",
      "model_strategy": "bear_bonus_phase8",
      "preference_model_valid": "",
      "p_draw": "",
      "p_draw_pct": "",
      "p_preference_draw": "",
      "quota_2026_total": ""
    },
    {
      "hunt_code": "BR7214",
      "hunt_name": "Paunsaugunt",
      "species": "Black Bear",
      "hunt_type": "Limited Entry - Fall",
      "residency": "Nonresident",
      "points": "",
      "draw_pool": "standard",
      "draw_system_type": "BEAR_DRAW",
      "algorithm_status": "IN_SCOPE_MODEL_PENDING",
      "reason": "Public limited-entry and restricted-pursuit bear rows use the Utah bonus model only when the source history proves real draw status, valid quota, and modeled bonus probabilities.",
      "model_strategy": "bear_bonus_phase8",
      "preference_model_valid": "",
      "p_draw": "",
      "p_draw_pct": "",
      "p_preference_draw": "",
      "quota_2026_total": ""
    },
    {
      "hunt_code": "BR7216",
      "hunt_name": "Fishlake/Thousand Lakes",
      "species": "Black Bear",
      "hunt_type": "Limited Entry - Fall",
      "residency": "Nonresident",
      "points": "",
      "draw_pool": "standard",
      "draw_system_type": "BEAR_DRAW",
      "algorithm_status": "IN_SCOPE_MODEL_PENDING",
      "reason": "Public limited-entry and restricted-pursuit bear rows use the Utah bonus model only when the source history proves real draw status, valid quota, and modeled bonus probabilities.",
      "model_strategy": "bear_bonus_phase8",
      "preference_model_valid": "",
      "p_draw": "",
      "p_draw_pct": "",
      "p_preference_draw": "",
      "quota_2026_total": ""
    },
    {
      "hunt_code": "BR7217",
      "hunt_name": "San Juan",
      "species": "Black Bear",
      "hunt_type": "Limited Entry - Fall",
      "residency": "Nonresident",
      "points": "",
      "draw_pool": "standard",
      "draw_system_type": "BEAR_DRAW",
      "algorithm_status": "IN_SCOPE_MODEL_PENDING",
      "reason": "Public limited-entry and restricted-pursuit bear rows use the Utah bonus model only when the source history proves real draw status, valid quota, and modeled bonus probabilities.",
      "model_strategy": "bear_bonus_phase8",
      "preference_model_valid": "",
      "p_draw": "",
      "p_draw_pct": "",
      "p_preference_draw": "",
      "quota_2026_total": ""
    },
    {
      "hunt_code": "BR7218",
      "hunt_name": "Diamond Mtn/Vernal/Bonanza",
      "species": "Black Bear",
      "hunt_type": "Limited Entry - Fall",
      "residency": "Nonresident",
      "points": "",
      "draw_pool": "standard",
      "draw_system_type": "BEAR_DRAW",
      "algorithm_status": "IN_SCOPE_MODEL_PENDING",
      "reason": "Public limited-entry and restricted-pursuit bear rows use the Utah bonus model only when the source history proves real draw status, valid quota, and modeled bonus probabilities.",
      "model_strategy": "bear_bonus_phase8",
      "preference_model_valid": "",
      "p_draw": "",
      "p_draw_pct": "",
      "p_preference_draw": "",
      "quota_2026_total": ""
    },
    {
      "hunt_code": "BR7219",
      "hunt_name": "Yellowstone",
      "species": "Black Bear",
      "hunt_type": "Limited Entry - Fall",
      "residency": "Nonresident",
      "points": "",
      "draw_pool": "standard",
      "draw_system_type": "BEAR_DRAW",
      "algorithm_status": "IN_SCOPE_MODEL_PENDING",
      "reason": "Public limited-entry and restricted-pursuit bear rows use the Utah bonus model only when the source history proves real draw status, valid quota, and modeled bonus probabilities.",
      "model_strategy": "bear_bonus_phase8",
      "preference_model_valid": "",
      "p_draw": "",
      "p_draw_pct": "",
      "p_preference_draw": "",
      "quota_2026_total": ""
    },
    {
      "hunt_code": "BR7220",
      "hunt_name": "Wasatch Mtns Avintaquin/Currant Creek",
      "species": "Black Bear",
      "hunt_type": "Limited Entry - Fall",
      "residency": "Nonresident",
      "points": "",
      "draw_pool": "standard",
      "draw_system_type": "BEAR_DRAW",
      "algorithm_status": "IN_SCOPE_MODEL_PENDING",
      "reason": "Public limited-entry and restricted-pursuit bear rows use the Utah bonus model only when the source history proves real draw status, valid quota, and modeled bonus probabilities.",
      "model_strategy": "bear_bonus_phase8",
      "preference_model_valid": "",
      "p_draw": "",
      "p_draw_pct": "",
      "p_preference_draw": "",
      "quota_2026_total": ""
    },
    {
      "hunt_code": "BR7225",
      "hunt_name": "Book Cliffs Little Creek Roadless",
      "species": "Black Bear",
      "hunt_type": "Spot and Stalk",
      "residency": "Nonresident",
      "points": "",
      "draw_pool": "standard",
      "draw_system_type": "BEAR_DRAW",
      "algorithm_status": "IN_SCOPE_MODEL_PENDING",
      "reason": "Public limited-entry and restricted-pursuit bear rows use the Utah bonus model only when the source history proves real draw status, valid quota, and modeled bonus probabilities.",
      "model_strategy": "bear_bonus_phase8",
      "preference_model_valid": "",
      "p_draw": "",
      "p_draw_pct": "",
      "p_preference_draw": "",
      "quota_2026_total": ""
    },
    {
      "hunt_code": "BR7228",
      "hunt_name": "Cache/Ogden",
      "species": "Black Bear",
      "hunt_type": "Limited Entry - Fall",
      "residency": "Nonresident",
      "points": "",
      "draw_pool": "standard",
      "draw_system_type": "BEAR_DRAW",
      "algorithm_status": "IN_SCOPE_MODEL_PENDING",
      "reason": "Public limited-entry and restricted-pursuit bear rows use the Utah bonus model only when the source history proves real draw status, valid quota, and modeled bonus probabilities.",
      "model_strategy": "bear_bonus_phase8",
      "preference_model_valid": "",
      "p_draw": "",
      "p_draw_pct": "",
      "p_preference_draw": "",
      "quota_2026_total": ""
    },
    {
      "hunt_code": "BR7229",
      "hunt_name": "Kamas/North Slope Summit",
      "species": "Black Bear",
      "hunt_type": "Limited Entry - Fall",
      "residency": "Nonresident",
      "points": "",
      "draw_pool": "standard",
      "draw_system_type": "BEAR_DRAW",
      "algorithm_status": "IN_SCOPE_MODEL_PENDING",
      "reason": "Public limited-entry and restricted-pursuit bear rows use the Utah bonus model only when the source history proves real draw status, valid quota, and modeled bonus probabilities.",
      "model_strategy": "bear_bonus_phase8",
      "preference_model_valid": "",
      "p_draw": "",
      "p_draw_pct": "",
      "p_preference_draw": "",
      "quota_2026_total": ""
    },
    {
      "hunt_code": "BR7237",
      "hunt_name": "Monroe",
      "species": "Black Bear",
      "hunt_type": "Limited Entry - Fall",
      "residency": "Nonresident",
      "points": "",
      "draw_pool": "standard",
      "draw_system_type": "BEAR_DRAW",
      "algorithm_status": "IN_SCOPE_MODEL_PENDING",
      "reason": "Public limited-entry and restricted-pursuit bear rows use the Utah bonus model only when the source history proves real draw status, valid quota, and modeled bonus probabilities.",
      "model_strategy": "bear_bonus_phase8",
      "preference_model_valid": "",
      "p_draw": "",
      "p_draw_pct": "",
      "p_preference_draw": "",
      "quota_2026_total": ""
    },
    {
      "hunt_code": "BR7238",
      "hunt_name": "Dolores Triangle",
      "species": "Black Bear",
      "hunt_type": "Limited Entry - Fall",
      "residency": "Nonresident",
      "points": "",
      "draw_pool": "standard",
      "draw_system_type": "BEAR_DRAW",
      "algorithm_status": "IN_SCOPE_MODEL_PENDING",
      "reason": "Public limited-entry and restricted-pursuit bear rows use the Utah bonus model only when the source history proves real draw status, valid quota, and modeled bonus probabilities.",
      "model_strategy": "bear_bonus_phase8",
      "preference_model_valid": "",
      "p_draw": "",
      "p_draw_pct": "",
      "p_preference_draw": "",
      "quota_2026_total": ""
    },
    {
      "hunt_code": "BR7238",
      "hunt_name": "Dolores Triangle",
      "species": "Black Bear",
      "hunt_type": "Limited Entry - Fall",
      "residency": "Resident",
      "points": "",
      "draw_pool": "standard",
      "draw_system_type": "BEAR_DRAW",
      "algorithm_status": "IN_SCOPE_MODEL_PENDING",
      "reason": "Public limited-entry and restricted-pursuit bear rows use the Utah bonus model only when the source history proves real draw status, valid quota, and modeled bonus probabilities.",
      "model_strategy": "bear_bonus_phase8",
      "preference_model_valid": "",
      "p_draw": "",
      "p_draw_pct": "",
      "p_preference_draw": "",
      "quota_2026_total": ""
    },
    {
      "hunt_code": "BR7239",
      "hunt_name": "La Sal Mtns",
      "species": "Black Bear",
      "hunt_type": "Limited Entry - Fall",
      "residency": "Nonresident",
      "points": "",
      "draw_pool": "standard",
      "draw_system_type": "BEAR_DRAW",
      "algorithm_status": "IN_SCOPE_MODEL_PENDING",
      "reason": "Public limited-entry and restricted-pursuit bear rows use the Utah bonus model only when the source history proves real draw status, valid quota, and modeled bonus probabilities.",
      "model_strategy": "bear_bonus_phase8",
      "preference_model_valid": "",
      "p_draw": "",
      "p_draw_pct": "",
      "p_preference_draw": "",
      "quota_2026_total": ""
    },
    {
      "hunt_code": "BR7239",
      "hunt_name": "La Sal Mtns",
      "species": "Black Bear",
      "hunt_type": "Limited Entry - Fall",
      "residency": "Resident",
      "points": "",
      "draw_pool": "standard",
      "draw_system_type": "BEAR_DRAW",
      "algorithm_status": "IN_SCOPE_MODEL_PENDING",
      "reason": "Public limited-entry and restricted-pursuit bear rows use the Utah bonus model only when the source history proves real draw status, valid quota, and modeled bonus probabilities.",
      "model_strategy": "bear_bonus_phase8",
      "preference_model_valid": "",
      "p_draw": "",
      "p_draw_pct": "",
      "p_preference_draw": "",
      "quota_2026_total": ""
    },
    {
      "hunt_code": "BR7301",
      "hunt_name": "Book Cliffs Little Creek Roadless",
      "species": "Black Bear",
      "hunt_type": "Limited Entry - Multiseason",
      "residency": "Nonresident",
      "points": "",
      "draw_pool": "standard",
      "draw_system_type": "BEAR_DRAW",
      "algorithm_status": "IN_SCOPE_MODEL_PENDING",
      "reason": "Public limited-entry and restricted-pursuit bear rows use the Utah bonus model only when the source history proves real draw status, valid quota, and modeled bonus probabilities.",
      "model_strategy": "bear_bonus_phase8",
      "preference_model_valid": "",
      "p_draw": "",
      "p_draw_pct": "",
      "p_preference_draw": "",
      "quota_2026_total": ""
    },
    {
      "hunt_code": "BR7305",
      "hunt_name": "Nebo",
      "species": "Black Bear",
      "hunt_type": "Limited Entry - Multiseason",
      "residency": "Nonresident",
      "points": "",
      "draw_pool": "standard",
      "draw_system_type": "BEAR_DRAW",
      "algorithm_status": "IN_SCOPE_MODEL_PENDING",
      "reason": "Public limited-entry and restricted-pursuit bear rows use the Utah bonus model only when the source history proves real draw status, valid quota, and modeled bonus probabilities.",
      "model_strategy": "bear_bonus_phase8",
      "preference_model_valid": "",
      "p_draw": "",
      "p_draw_pct": "",
      "p_preference_draw": "",
      "quota_2026_total": ""
    },
    {
      "hunt_code": "BR7308",
      "hunt_name": "North Slope Three Corners/West Daggett",
      "species": "Black Bear",
      "hunt_type": "Limited Entry - Multiseason",
      "residency": "Nonresident",
      "points": "",
      "draw_pool": "standard",
      "draw_system_type": "BEAR_DRAW",
      "algorithm_status": "IN_SCOPE_MODEL_PENDING",
      "reason": "Public limited-entry and restricted-pursuit bear rows use the Utah bonus model only when the source history proves real draw status, valid quota, and modeled bonus probabilities.",
      "model_strategy": "bear_bonus_phase8",
      "preference_model_valid": "",
      "p_draw": "",
      "p_draw_pct": "",
      "p_preference_draw": "",
      "quota_2026_total": ""
    },
    {
      "hunt_code": "BR7309",
      "hunt_name": "Panguitch Lake/Zion",
      "species": "Black Bear",
      "hunt_type": "Limited Entry - Multiseason",
      "residency": "Nonresident",
      "points": "",
      "draw_pool": "standard",
      "draw_system_type": "BEAR_DRAW",
      "algorithm_status": "IN_SCOPE_MODEL_PENDING",
      "reason": "Public limited-entry and restricted-pursuit bear rows use the Utah bonus model only when the source history proves real draw status, valid quota, and modeled bonus probabilities.",
      "model_strategy": "bear_bonus_phase8",
      "preference_model_valid": "",
      "p_draw": "",
      "p_draw_pct": "",
      "p_preference_draw": "",
      "quota_2026_total": ""
    },
    {
      "hunt_code": "BR7311",
      "hunt_name": "Fishlake/Thousand Lakes",
      "species": "Black Bear",
      "hunt_type": "Limited Entry - Multiseason",
      "residency": "Nonresident",
      "points": "",
      "draw_pool": "standard",
      "draw_system_type": "BEAR_DRAW",
      "algorithm_status": "IN_SCOPE_MODEL_PENDING",
      "reason": "Public limited-entry and restricted-pursuit bear rows use the Utah bonus model only when the source history proves real draw status, valid quota, and modeled bonus probabilities.",
      "model_strategy": "bear_bonus_phase8",
      "preference_model_valid": "",
      "p_draw": "",
      "p_draw_pct": "",
      "p_preference_draw": "",
      "quota_2026_total": ""
    },
    {
      "hunt_code": "BR7313",
      "hunt_name": "Diamond Mtn/Vernal/Bonanza",
      "species": "Black Bear",
      "hunt_type": "Limited Entry - Multiseason",
      "residency": "Nonresident",
      "points": "",
      "draw_pool": "standard",
      "draw_system_type": "BEAR_DRAW",
      "algorithm_status": "IN_SCOPE_MODEL_PENDING",
      "reason": "Public limited-entry and restricted-pursuit bear rows use the Utah bonus model only when the source history proves real draw status, valid quota, and modeled bonus probabilities.",
      "model_strategy": "bear_bonus_phase8",
      "preference_model_valid": "",
      "p_draw": "",
      "p_draw_pct": "",
      "p_preference_draw": "",
      "quota_2026_total": ""
    },
    {
      "hunt_code": "BR7314",
      "hunt_name": "Yellowstone",
      "species": "Black Bear",
      "hunt_type": "Limited Entry - Multiseason",
      "residency": "Nonresident",
      "points": "",
      "draw_pool": "standard",
      "draw_system_type": "BEAR_DRAW",
      "algorithm_status": "IN_SCOPE_MODEL_PENDING",
      "reason": "Public limited-entry and restricted-pursuit bear rows use the Utah bonus model only when the source history proves real draw status, valid quota, and modeled bonus probabilities.",
      "model_strategy": "bear_bonus_phase8",
      "preference_model_valid": "",
      "p_draw": "",
      "p_draw_pct": "",
      "p_preference_draw": "",
      "quota_2026_total": ""
    },
    {
      "hunt_code": "BR7315",
      "hunt_name": "Wasatch Mtns Avintaquin/Currant Creek",
      "species": "Black Bear",
      "hunt_type": "Limited Entry - Multiseason",
      "residency": "Nonresident",
      "points": "",
      "draw_pool": "standard",
      "draw_system_type": "BEAR_DRAW",
      "algorithm_status": "IN_SCOPE_MODEL_PENDING",
      "reason": "Public limited-entry and restricted-pursuit bear rows use the Utah bonus model only when the source history proves real draw status, valid quota, and modeled bonus probabilities.",
      "model_strategy": "bear_bonus_phase8",
      "preference_model_valid": "",
      "p_draw": "",
      "p_draw_pct": "",
      "p_preference_draw": "",
      "quota_2026_total": ""
    },
    {
      "hunt_code": "BR7317",
      "hunt_name": "Nine Mile",
      "species": "Black Bear",
      "hunt_type": "Limited Entry - Multiseason",
      "residency": "Nonresident",
      "points": "",
      "draw_pool": "standard",
      "draw_system_type": "BEAR_DRAW",
      "algorithm_status": "IN_SCOPE_MODEL_PENDING",
      "reason": "Public limited-entry and restricted-pursuit bear rows use the Utah bonus model only when the source history proves real draw status, valid quota, and modeled bonus probabilities.",
      "model_strategy": "bear_bonus_phase8",
      "preference_model_valid": "",
      "p_draw": "",
      "p_draw_pct": "",
      "p_preference_draw": "",
      "quota_2026_total": ""
    },
    {
      "hunt_code": "BR7318",
      "hunt_name": "Beaver",
      "species": "Black Bear",
      "hunt_type": "Limited Entry - Multiseason",
      "residency": "Nonresident",
      "points": "",
      "draw_pool": "standard",
      "draw_system_type": "BEAR_DRAW",
      "algorithm_status": "IN_SCOPE_MODEL_PENDING",
      "reason": "Public limited-entry and restricted-pursuit bear rows use the Utah bonus model only when the source history proves real draw status, valid quota, and modeled bonus probabilities.",
      "model_strategy": "bear_bonus_phase8",
      "preference_model_valid": "",
      "p_draw": "",
      "p_draw_pct": "",
      "p_preference_draw": "",
      "quota_2026_total": ""
    },
    {
      "hunt_code": "BR7320",
      "hunt_name": "Cache/Ogden",
      "species": "Black Bear",
      "hunt_type": "Limited Entry - Multiseason",
      "residency": "Nonresident",
      "points": "",
      "draw_pool": "standard",
      "draw_system_type": "BEAR_DRAW",
      "algorithm_status": "IN_SCOPE_MODEL_PENDING",
      "reason": "Public limited-entry and restricted-pursuit bear rows use the Utah bonus model only when the source history proves real draw status, valid quota, and modeled bonus probabilities.",
      "model_strategy": "bear_bonus_phase8",
      "preference_model_valid": "",
      "p_draw": "",
      "p_draw_pct": "",
      "p_preference_draw": "",
      "quota_2026_total": ""
    },
    {
      "hunt_code": "BR7321",
      "hunt_name": "Kamas/North Slope Summit",
      "species": "Black Bear",
      "hunt_type": "Limited Entry - Multiseason",
      "residency": "Nonresident",
      "points": "",
      "draw_pool": "standard",
      "draw_system_type": "BEAR_DRAW",
      "algorithm_status": "IN_SCOPE_MODEL_PENDING",
      "reason": "Public limited-entry and restricted-pursuit bear rows use the Utah bonus model only when the source history proves real draw status, valid quota, and modeled bonus probabilities.",
      "model_strategy": "bear_bonus_phase8",
      "preference_model_valid": "",
      "p_draw": "",
      "p_draw_pct": "",
      "p_preference_draw": "",
      "quota_2026_total": ""
    },
    {
      "hunt_code": "BR7322",
      "hunt_name": "Mt Dutton",
      "species": "Black Bear",
      "hunt_type": "Limited Entry - Multiseason",
      "residency": "Nonresident",
      "points": "",
      "draw_pool": "standard",
      "draw_system_type": "BEAR_DRAW",
      "algorithm_status": "IN_SCOPE_MODEL_PENDING",
      "reason": "Public limited-entry and restricted-pursuit bear rows use the Utah bonus model only when the source history proves real draw status, valid quota, and modeled bonus probabilities.",
      "model_strategy": "bear_bonus_phase8",
      "preference_model_valid": "",
      "p_draw": "",
      "p_draw_pct": "",
      "p_preference_draw": "",
      "quota_2026_total": ""
    },
    {
      "hunt_code": "BR7323",
      "hunt_name": "Paunsaugunt",
      "species": "Black Bear",
      "hunt_type": "Limited Entry - Multiseason",
      "residency": "Nonresident",
      "points": "",
      "draw_pool": "standard",
      "draw_system_type": "BEAR_DRAW",
      "algorithm_status": "IN_SCOPE_MODEL_PENDING",
      "reason": "Public limited-entry and restricted-pursuit bear rows use the Utah bonus model only when the source history proves real draw status, valid quota, and modeled bonus probabilities.",
      "model_strategy": "bear_bonus_phase8",
      "preference_model_valid": "",
      "p_draw": "",
      "p_draw_pct": "",
      "p_preference_draw": "",
      "quota_2026_total": ""
    },
    {
      "hunt_code": "BR7325",
      "hunt_name": "Chalk Creek/East Canyon/Morgan-South Rich",
      "species": "Black Bear",
      "hunt_type": "Limited Entry - Multiseason",
      "residency": "Nonresident",
      "points": "",
      "draw_pool": "standard",
      "draw_system_type": "BEAR_DRAW",
      "algorithm_status": "IN_SCOPE_MODEL_PENDING",
      "reason": "Public limited-entry and restricted-pursuit bear rows use the Utah bonus model only when the source history proves real draw status, valid quota, and modeled bonus probabilities.",
      "model_strategy": "bear_bonus_phase8",
      "preference_model_valid": "",
      "p_draw": "",
      "p_draw_pct": "",
      "p_preference_draw": "",
      "quota_2026_total": ""
    },
    {
      "hunt_code": "BR7326",
      "hunt_name": "La Sal Mtns",
      "species": "Black Bear",
      "hunt_type": "Limited Entry - Multiseason",
      "residency": "Nonresident",
      "points": "",
      "draw_pool": "standard",
      "draw_system_type": "BEAR_DRAW",
      "algorithm_status": "IN_SCOPE_MODEL_PENDING",
      "reason": "Public limited-entry and restricted-pursuit bear rows use the Utah bonus model only when the source history proves real draw status, valid quota, and modeled bonus probabilities.",
      "model_strategy": "bear_bonus_phase8",
      "preference_model_valid": "",
      "p_draw": "",
      "p_draw_pct": "",
      "p_preference_draw": "",
      "quota_2026_total": ""
    },
    {
      "hunt_code": "BR7326",
      "hunt_name": "La Sal Mtns",
      "species": "Black Bear",
      "hunt_type": "Limited Entry - Multiseason",
      "residency": "Resident",
      "points": "",
      "draw_pool": "standard",
      "draw_system_type": "BEAR_DRAW",
      "algorithm_status": "IN_SCOPE_MODEL_PENDING",
      "reason": "Public limited-entry and restricted-pursuit bear rows use the Utah bonus model only when the source history proves real draw status, valid quota, and modeled bonus probabilities.",
      "model_strategy": "bear_bonus_phase8",
      "preference_model_valid": "",
      "p_draw": "",
      "p_draw_pct": "",
      "p_preference_draw": "",
      "quota_2026_total": ""
    },
    {
      "hunt_code": "DA1011",
      "hunt_name": "George Creek CWMU",
      "species": "Deer",
      "hunt_type": "CWMU",
      "residency": "Nonresident",
      "points": "",
      "draw_pool": "standard",
      "draw_system_type": "BONUS_CWMU_BIG_GAME",
      "algorithm_status": "IN_SCOPE_MODEL_PENDING",
      "reason": "Public CWMU big-game permits use the Utah bonus model and only promote rows with proven public-draw source data, valid quota, and modeled bonus probabilities.",
      "model_strategy": "bonus_special_phase6",
      "preference_model_valid": "",
      "p_draw": "",
      "p_draw_pct": "",
      "p_preference_draw": "",
      "quota_2026_total": ""
    },
    {
      "hunt_code": "DA1012",
      "hunt_name": "Junction Valley CWMU",
      "species": "Deer",
      "hunt_type": "CWMU",
      "residency": "Nonresident",
      "points": "",
      "draw_pool": "standard",
      "draw_system_type": "BONUS_CWMU_BIG_GAME",
      "algorithm_status": "IN_SCOPE_MODEL_PENDING",
      "reason": "Public CWMU big-game permits use the Utah bonus model and only promote rows with proven public-draw source data, valid quota, and modeled bonus probabilities.",
      "model_strategy": "bonus_special_phase6",
      "preference_model_valid": "",
      "p_draw": "",
      "p_draw_pct": "",
      "p_preference_draw": "",
      "quota_2026_total": ""
    },
    {
      "hunt_code": "DA1013",
      "hunt_name": "Mt Carmel CWMU",
      "species": "Deer",
      "hunt_type": "CWMU",
      "residency": "Nonresident",
      "points": "",
      "draw_pool": "standard",
      "draw_system_type": "BONUS_CWMU_BIG_GAME",
      "algorithm_status": "IN_SCOPE_MODEL_PENDING",
      "reason": "Public CWMU big-game permits use the Utah bonus model and only promote rows with proven public-draw source data, valid quota, and modeled bonus probabilities.",
      "model_strategy": "bonus_special_phase6",
      "preference_model_valid": "",
      "p_draw": "",
      "p_draw_pct": "",
      "p_preference_draw": "",
      "quota_2026_total": ""
    },
    {
      "hunt_code": "DA1050",
      "hunt_name": "The Rose of Snowville CWMU",
      "species": "Deer",
      "hunt_type": "CWMU",
      "residency": "Nonresident",
      "points": "",
      "draw_pool": "standard",
      "draw_system_type": "BONUS_CWMU_BIG_GAME",
      "algorithm_status": "IN_SCOPE_MODEL_PENDING",
      "reason": "Public CWMU big-game permits use the Utah bonus model and only promote rows with proven public-draw source data, valid quota, and modeled bonus probabilities.",
      "model_strategy": "bonus_special_phase6",
      "preference_model_valid": "",
      "p_draw": "",
      "p_draw_pct": "",
      "p_preference_draw": "",
      "quota_2026_total": ""
    },
    {
      "hunt_code": "DA1050",
      "hunt_name": "The Rose of Snowville CWMU",
      "species": "Deer",
      "hunt_type": "CWMU",
      "residency": "Resident",
      "points": "",
      "draw_pool": "standard",
      "draw_system_type": "BONUS_CWMU_BIG_GAME",
      "algorithm_status": "IN_SCOPE_MODEL_PENDING",
      "reason": "Public CWMU big-game permits use the Utah bonus model and only promote rows with proven public-draw source data, valid quota, and modeled bonus probabilities.",
      "model_strategy": "bonus_special_phase6",
      "preference_model_valid": "",
      "p_draw": "",
      "p_draw_pct": "",
      "p_preference_draw": "",
      "quota_2026_total": ""
    },
    {
      "hunt_code": "DB1009",
      "hunt_name": "Henry Mtns (Management Buck Deer)",
      "species": "Deer",
      "hunt_type": "Premium Limited Entry",
      "residency": "Nonresident",
      "points": "0",
      "draw_pool": "standard",
      "draw_system_type": "PREFERENCE_GENERAL_SEASON_BUCK_DEER",
      "algorithm_status": "IN_SCOPE_MODEL_PENDING",
      "reason": "General-season buck deer uses a preference-point model and only promotes rows with valid source history, quota, and modeled preference probabilities.",
      "model_strategy": "",
      "preference_model_valid": "",
      "p_draw": "",
      "p_draw_pct": "",
      "p_preference_draw": "",
      "quota_2026_total": "1"
    },
    {
      "hunt_code": "DB1009",
      "hunt_name": "Henry Mtns (Management Buck Deer)",
      "species": "Deer",
      "hunt_type": "Premium Limited Entry",
      "residency": "Nonresident",
      "points": "1",
      "draw_pool": "standard",
      "draw_system_type": "PREFERENCE_GENERAL_SEASON_BUCK_DEER",
      "algorithm_status": "IN_SCOPE_MODEL_PENDING",
      "reason": "General-season buck deer uses a preference-point model and only promotes rows with valid source history, quota, and modeled preference probabilities.",
      "model_strategy": "",
      "preference_model_valid": "",
      "p_draw": "",
      "p_draw_pct": "",
      "p_preference_draw": "",
      "quota_2026_total": "1"
    },
    {
      "hunt_code": "DB1009",
      "hunt_name": "Henry Mtns (Management Buck Deer)",
      "species": "Deer",
      "hunt_type": "Premium Limited Entry",
      "residency": "Nonresident",
      "points": "2",
      "draw_pool": "standard",
      "draw_system_type": "PREFERENCE_GENERAL_SEASON_BUCK_DEER",
      "algorithm_status": "IN_SCOPE_MODEL_PENDING",
      "reason": "General-season buck deer uses a preference-point model and only promotes rows with valid source history, quota, and modeled preference probabilities.",
      "model_strategy": "",
      "preference_model_valid": "",
      "p_draw": "",
      "p_draw_pct": "",
      "p_preference_draw": "",
      "quota_2026_total": "1"
    },
    {
      "hunt_code": "DB1009",
      "hunt_name": "Henry Mtns (Management Buck Deer)",
      "species": "Deer",
      "hunt_type": "Premium Limited Entry",
      "residency": "Nonresident",
      "points": "3",
      "draw_pool": "standard",
      "draw_system_type": "PREFERENCE_GENERAL_SEASON_BUCK_DEER",
      "algorithm_status": "IN_SCOPE_MODEL_PENDING",
      "reason": "General-season buck deer uses a preference-point model and only promotes rows with valid source history, quota, and modeled preference probabilities.",
      "model_strategy": "",
      "preference_model_valid": "",
      "p_draw": "",
      "p_draw_pct": "",
      "p_preference_draw": "",
      "quota_2026_total": "1"
    },
    {
      "hunt_code": "DB1009",
      "hunt_name": "Henry Mtns (Management Buck Deer)",
      "species": "Deer",
      "hunt_type": "Premium Limited Entry",
      "residency": "Nonresident",
      "points": "4",
      "draw_pool": "standard",
      "draw_system_type": "PREFERENCE_GENERAL_SEASON_BUCK_DEER",
      "algorithm_status": "IN_SCOPE_MODEL_PENDING",
      "reason": "General-season buck deer uses a preference-point model and only promotes rows with valid source history, quota, and modeled preference probabilities.",
      "model_strategy": "",
      "preference_model_valid": "",
      "p_draw": "",
      "p_draw_pct": "",
      "p_preference_draw": "",
      "quota_2026_total": "1"
    },
    {
      "hunt_code": "DB1009",
      "hunt_name": "Henry Mtns (Management Buck Deer)",
      "species": "Deer",
      "hunt_type": "Premium Limited Entry",
      "residency": "Nonresident",
      "points": "5",
      "draw_pool": "standard",
      "draw_system_type": "PREFERENCE_GENERAL_SEASON_BUCK_DEER",
      "algorithm_status": "IN_SCOPE_MODEL_PENDING",
      "reason": "General-season buck deer uses a preference-point model and only promotes rows with valid source history, quota, and modeled preference probabilities.",
      "model_strategy": "",
      "preference_model_valid": "",
      "p_draw": "",
      "p_draw_pct": "",
      "p_preference_draw": "",
      "quota_2026_total": "1"
    },
    {
      "hunt_code": "DB1009",
      "hunt_name": "Henry Mtns (Management Buck Deer)",
      "species": "Deer",
      "hunt_type": "Premium Limited Entry",
      "residency": "Nonresident",
      "points": "6",
      "draw_pool": "standard",
      "draw_system_type": "PREFERENCE_GENERAL_SEASON_BUCK_DEER",
      "algorithm_status": "IN_SCOPE_MODEL_PENDING",
      "reason": "General-season buck deer uses a preference-point model and only promotes rows with valid source history, quota, and modeled preference probabilities.",
      "model_strategy": "",
      "preference_model_valid": "",
      "p_draw": "",
      "p_draw_pct": "",
      "p_preference_draw": "",
      "quota_2026_total": "1"
    },
    {
      "hunt_code": "DB1009",
      "hunt_name": "Henry Mtns (Management Buck Deer)",
      "species": "Deer",
      "hunt_type": "Premium Limited Entry",
      "residency": "Nonresident",
      "points": "7",
      "draw_pool": "standard",
      "draw_system_type": "PREFERENCE_GENERAL_SEASON_BUCK_DEER",
      "algorithm_status": "IN_SCOPE_MODEL_PENDING",
      "reason": "General-season buck deer uses a preference-point model and only promotes rows with valid source history, quota, and modeled preference probabilities.",
      "model_strategy": "",
      "preference_model_valid": "",
      "p_draw": "",
      "p_draw_pct": "",
      "p_preference_draw": "",
      "quota_2026_total": "1"
    },
    {
      "hunt_code": "DB1009",
      "hunt_name": "Henry Mtns (Management Buck Deer)",
      "species": "Deer",
      "hunt_type": "Premium Limited Entry",
      "residency": "Nonresident",
      "points": "8",
      "draw_pool": "standard",
      "draw_system_type": "PREFERENCE_GENERAL_SEASON_BUCK_DEER",
      "algorithm_status": "IN_SCOPE_MODEL_PENDING",
      "reason": "General-season buck deer uses a preference-point model and only promotes rows with valid source history, quota, and modeled preference probabilities.",
      "model_strategy": "",
      "preference_model_valid": "",
      "p_draw": "",
      "p_draw_pct": "",
      "p_preference_draw": "",
      "quota_2026_total": "1"
    },
    {
      "hunt_code": "DB1009",
      "hunt_name": "Henry Mtns (Management Buck Deer)",
      "species": "Deer",
      "hunt_type": "Premium Limited Entry",
      "residency": "Nonresident",
      "points": "9",
      "draw_pool": "standard",
      "draw_system_type": "PREFERENCE_GENERAL_SEASON_BUCK_DEER",
      "algorithm_status": "IN_SCOPE_MODEL_PENDING",
      "reason": "General-season buck deer uses a preference-point model and only promotes rows with valid source history, quota, and modeled preference probabilities.",
      "model_strategy": "",
      "preference_model_valid": "",
      "p_draw": "",
      "p_draw_pct": "",
      "p_preference_draw": "",
      "quota_2026_total": "1"
    },
    {
      "hunt_code": "DB1009",
      "hunt_name": "Henry Mtns (Management Buck Deer)",
      "species": "Deer",
      "hunt_type": "Premium Limited Entry",
      "residency": "Nonresident",
      "points": "10",
      "draw_pool": "standard",
      "draw_system_type": "PREFERENCE_GENERAL_SEASON_BUCK_DEER",
      "algorithm_status": "IN_SCOPE_MODEL_PENDING",
      "reason": "General-season buck deer uses a preference-point model and only promotes rows with valid source history, quota, and modeled preference probabilities.",
      "model_strategy": "",
      "preference_model_valid": "",
      "p_draw": "",
      "p_draw_pct": "",
      "p_preference_draw": "",
      "quota_2026_total": "1"
    },
    {
      "hunt_code": "DB1009",
      "hunt_name": "Henry Mtns (Management Buck Deer)",
      "species": "Deer",
      "hunt_type": "Premium Limited Entry",
      "residency": "Nonresident",
      "points": "11",
      "draw_pool": "standard",
      "draw_system_type": "PREFERENCE_GENERAL_SEASON_BUCK_DEER",
      "algorithm_status": "IN_SCOPE_MODEL_PENDING",
      "reason": "General-season buck deer uses a preference-point model and only promotes rows with valid source history, quota, and modeled preference probabilities.",
      "model_strategy": "",
      "preference_model_valid": "",
      "p_draw": "",
      "p_draw_pct": "",
      "p_preference_draw": "",
      "quota_2026_total": "1"
    },
    {
      "hunt_code": "DB1009",
      "hunt_name": "Henry Mtns (Management Buck Deer)",
      "species": "Deer",
      "hunt_type": "Premium Limited Entry",
      "residency": "Nonresident",
      "points": "12",
      "draw_pool": "standard",
      "draw_system_type": "PREFERENCE_GENERAL_SEASON_BUCK_DEER",
      "algorithm_status": "IN_SCOPE_MODEL_PENDING",
      "reason": "General-season buck deer uses a preference-point model and only promotes rows with valid source history, quota, and modeled preference probabilities.",
      "model_strategy": "",
      "preference_model_valid": "",
      "p_draw": "",
      "p_draw_pct": "",
      "p_preference_draw": "",
      "quota_2026_total": "1"
    },
    {
      "hunt_code": "DB1009",
      "hunt_name": "Henry Mtns (Management Buck Deer)",
      "species": "Deer",
      "hunt_type": "Premium Limited Entry",
      "residency": "Nonresident",
      "points": "13",
      "draw_pool": "standard",
      "draw_system_type": "PREFERENCE_GENERAL_SEASON_BUCK_DEER",
      "algorithm_status": "IN_SCOPE_MODEL_PENDING",
      "reason": "General-season buck deer uses a preference-point model and only promotes rows with valid source history, quota, and modeled preference probabilities.",
      "model_strategy": "",
      "preference_model_valid": "",
      "p_draw": "",
      "p_draw_pct": "",
      "p_preference_draw": "",
      "quota_2026_total": "1"
    },
    {
      "hunt_code": "DB1009",
      "hunt_name": "Henry Mtns (Management Buck Deer)",
      "species": "Deer",
      "hunt_type": "Premium Limited Entry",
      "residency": "Nonresident",
      "points": "14",
      "draw_pool": "standard",
      "draw_system_type": "PREFERENCE_GENERAL_SEASON_BUCK_DEER",
      "algorithm_status": "IN_SCOPE_MODEL_PENDING",
      "reason": "General-season buck deer uses a preference-point model and only promotes rows with valid source history, quota, and modeled preference probabilities.",
      "model_strategy": "",
      "preference_model_valid": "",
      "p_draw": "",
      "p_draw_pct": "",
      "p_preference_draw": "",
      "quota_2026_total": "1"
    },
    {
      "hunt_code": "DB1009",
      "hunt_name": "Henry Mtns (Management Buck Deer)",
      "species": "Deer",
      "hunt_type": "Premium Limited Entry",
      "residency": "Nonresident",
      "points": "15",
      "draw_pool": "standard",
      "draw_system_type": "PREFERENCE_GENERAL_SEASON_BUCK_DEER",
      "algorithm_status": "IN_SCOPE_MODEL_PENDING",
      "reason": "General-season buck deer uses a preference-point model and only promotes rows with valid source history, quota, and modeled preference probabilities.",
      "model_strategy": "",
      "preference_model_valid": "",
      "p_draw": "",
      "p_draw_pct": "",
      "p_preference_draw": "",
      "quota_2026_total": "1"
    },
    {
      "hunt_code": "DB1009",
      "hunt_name": "Henry Mtns (Management Buck Deer)",
      "species": "Deer",
      "hunt_type": "Premium Limited Entry",
      "residency": "Nonresident",
      "points": "16",
      "draw_pool": "standard",
      "draw_system_type": "PREFERENCE_GENERAL_SEASON_BUCK_DEER",
      "algorithm_status": "IN_SCOPE_MODEL_PENDING",
      "reason": "General-season buck deer uses a preference-point model and only promotes rows with valid source history, quota, and modeled preference probabilities.",
      "model_strategy": "",
      "preference_model_valid": "",
      "p_draw": "",
      "p_draw_pct": "",
      "p_preference_draw": "",
      "quota_2026_total": "1"
    },
    {
      "hunt_code": "DB1009",
      "hunt_name": "Henry Mtns (Management Buck Deer)",
      "species": "Deer",
      "hunt_type": "Premium Limited Entry",
      "residency": "Nonresident",
      "points": "17",
      "draw_pool": "standard",
      "draw_system_type": "PREFERENCE_GENERAL_SEASON_BUCK_DEER",
      "algorithm_status": "IN_SCOPE_MODEL_PENDING",
      "reason": "General-season buck deer uses a preference-point model and only promotes rows with valid source history, quota, and modeled preference probabilities.",
      "model_strategy": "",
      "preference_model_valid": "",
      "p_draw": "",
      "p_draw_pct": "",
      "p_preference_draw": "",
      "quota_2026_total": "1"
    },
    {
      "hunt_code": "DB1009",
      "hunt_name": "Henry Mtns (Management Buck Deer)",
      "species": "Deer",
      "hunt_type": "Premium Limited Entry",
      "residency": "Nonresident",
      "points": "18",
      "draw_pool": "standard",
      "draw_system_type": "PREFERENCE_GENERAL_SEASON_BUCK_DEER",
      "algorithm_status": "IN_SCOPE_MODEL_PENDING",
      "reason": "General-season buck deer uses a preference-point model and only promotes rows with valid source history, quota, and modeled preference probabilities.",
      "model_strategy": "",
      "preference_model_valid": "",
      "p_draw": "",
      "p_draw_pct": "",
      "p_preference_draw": "",
      "quota_2026_total": "1"
    },
    {
      "hunt_code": "DB1009",
      "hunt_name": "Henry Mtns (Management Buck Deer)",
      "species": "Deer",
      "hunt_type": "Premium Limited Entry",
      "residency": "Nonresident",
      "points": "19",
      "draw_pool": "standard",
      "draw_system_type": "PREFERENCE_GENERAL_SEASON_BUCK_DEER",
      "algorithm_status": "IN_SCOPE_MODEL_PENDING",
      "reason": "General-season buck deer uses a preference-point model and only promotes rows with valid source history, quota, and modeled preference probabilities.",
      "model_strategy": "",
      "preference_model_valid": "",
      "p_draw": "",
      "p_draw_pct": "",
      "p_preference_draw": "",
      "quota_2026_total": "1"
    },
    {
      "hunt_code": "DB1009",
      "hunt_name": "Henry Mtns (Management Buck Deer)",
      "species": "Deer",
      "hunt_type": "Premium Limited Entry",
      "residency": "Nonresident",
      "points": "20",
      "draw_pool": "standard",
      "draw_system_type": "PREFERENCE_GENERAL_SEASON_BUCK_DEER",
      "algorithm_status": "IN_SCOPE_MODEL_PENDING",
      "reason": "General-season buck deer uses a preference-point model and only promotes rows with valid source history, quota, and modeled preference probabilities.",
      "model_strategy": "",
      "preference_model_valid": "",
      "p_draw": "",
      "p_draw_pct": "",
      "p_preference_draw": "",
      "quota_2026_total": "1"
    },
    {
      "hunt_code": "DB1009",
      "hunt_name": "Henry Mtns (Management Buck Deer)",
      "species": "Deer",
      "hunt_type": "Premium Limited Entry",
      "residency": "Nonresident",
      "points": "21",
      "draw_pool": "standard",
      "draw_system_type": "PREFERENCE_GENERAL_SEASON_BUCK_DEER",
      "algorithm_status": "IN_SCOPE_MODEL_PENDING",
      "reason": "General-season buck deer uses a preference-point model and only promotes rows with valid source history, quota, and modeled preference probabilities.",
      "model_strategy": "",
      "preference_model_valid": "",
      "p_draw": "",
      "p_draw_pct": "",
      "p_preference_draw": "",
      "quota_2026_total": "1"
    },
    {
      "hunt_code": "DB1009",
      "hunt_name": "Henry Mtns (Management Buck Deer)",
      "species": "Deer",
      "hunt_type": "Premium Limited Entry",
      "residency": "Nonresident",
      "points": "22",
      "draw_pool": "standard",
      "draw_system_type": "PREFERENCE_GENERAL_SEASON_BUCK_DEER",
      "algorithm_status": "IN_SCOPE_MODEL_PENDING",
      "reason": "General-season buck deer uses a preference-point model and only promotes rows with valid source history, quota, and modeled preference probabilities.",
      "model_strategy": "",
      "preference_model_valid": "",
      "p_draw": "",
      "p_draw_pct": "",
      "p_preference_draw": "",
      "quota_2026_total": "1"
    },
    {
      "hunt_code": "DB1009",
      "hunt_name": "Henry Mtns (Management Buck Deer)",
      "species": "Deer",
      "hunt_type": "Premium Limited Entry",
      "residency": "Nonresident",
      "points": "23",
      "draw_pool": "standard",
      "draw_system_type": "PREFERENCE_GENERAL_SEASON_BUCK_DEER",
      "algorithm_status": "IN_SCOPE_MODEL_PENDING",
      "reason": "General-season buck deer uses a preference-point model and only promotes rows with valid source history, quota, and modeled preference probabilities.",
      "model_strategy": "",
      "preference_model_valid": "",
      "p_draw": "",
      "p_draw_pct": "",
      "p_preference_draw": "",
      "quota_2026_total": "1"
    },
    {
      "hunt_code": "DB1009",
      "hunt_name": "Henry Mtns (Management Buck Deer)",
      "species": "Deer",
      "hunt_type": "Premium Limited Entry",
      "residency": "Nonresident",
      "points": "24",
      "draw_pool": "standard",
      "draw_system_type": "PREFERENCE_GENERAL_SEASON_BUCK_DEER",
      "algorithm_status": "IN_SCOPE_MODEL_PENDING",
      "reason": "General-season buck deer uses a preference-point model and only promotes rows with valid source history, quota, and modeled preference probabilities.",
      "model_strategy": "",
      "preference_model_valid": "",
      "p_draw": "",
      "p_draw_pct": "",
      "p_preference_draw": "",
      "quota_2026_total": "1"
    },
    {
      "hunt_code": "DB1009",
      "hunt_name": "Henry Mtns (Management Buck Deer)",
      "species": "Deer",
      "hunt_type": "Premium Limited Entry",
      "residency": "Nonresident",
      "points": "25",
      "draw_pool": "standard",
      "draw_system_type": "PREFERENCE_GENERAL_SEASON_BUCK_DEER",
      "algorithm_status": "IN_SCOPE_MODEL_PENDING",
      "reason": "General-season buck deer uses a preference-point model and only promotes rows with valid source history, quota, and modeled preference probabilities.",
      "model_strategy": "",
      "preference_model_valid": "",
      "p_draw": "",
      "p_draw_pct": "",
      "p_preference_draw": "",
      "quota_2026_total": "1"
    },
    {
      "hunt_code": "DB1009",
      "hunt_name": "Henry Mtns (Management Buck Deer)",
      "species": "Deer",
      "hunt_type": "Premium Limited Entry",
      "residency": "Nonresident",
      "points": "26",
      "draw_pool": "standard",
      "draw_system_type": "PREFERENCE_GENERAL_SEASON_BUCK_DEER",
      "algorithm_status": "IN_SCOPE_MODEL_PENDING",
      "reason": "General-season buck deer uses a preference-point model and only promotes rows with valid source history, quota, and modeled preference probabilities.",
      "model_strategy": "",
      "preference_model_valid": "",
      "p_draw": "",
      "p_draw_pct": "",
      "p_preference_draw": "",
      "quota_2026_total": "1"
    },
    {
      "hunt_code": "DB1009",
      "hunt_name": "Henry Mtns (Management Buck Deer)",
      "species": "Deer",
      "hunt_type": "Premium Limited Entry",
      "residency": "Nonresident",
      "points": "27",
      "draw_pool": "standard",
      "draw_system_type": "PREFERENCE_GENERAL_SEASON_BUCK_DEER",
      "algorithm_status": "IN_SCOPE_MODEL_PENDING",
      "reason": "General-season buck deer uses a preference-point model and only promotes rows with valid source history, quota, and modeled preference probabilities.",
      "model_strategy": "",
      "preference_model_valid": "",
      "p_draw": "",
      "p_draw_pct": "",
      "p_preference_draw": "",
      "quota_2026_total": "1"
    },
    {
      "hunt_code": "DB1009",
      "hunt_name": "Henry Mtns (Management Buck Deer)",
      "species": "Deer",
      "hunt_type": "Premium Limited Entry",
      "residency": "Nonresident",
      "points": "28",
      "draw_pool": "standard",
      "draw_system_type": "PREFERENCE_GENERAL_SEASON_BUCK_DEER",
      "algorithm_status": "IN_SCOPE_MODEL_PENDING",
      "reason": "General-season buck deer uses a preference-point model and only promotes rows with valid source history, quota, and modeled preference probabilities.",
      "model_strategy": "",
      "preference_model_valid": "",
      "p_draw": "",
      "p_draw_pct": "",
      "p_preference_draw": "",
      "quota_2026_total": "1"
    },
    {
      "hunt_code": "DB1009",
      "hunt_name": "Henry Mtns (Management Buck Deer)",
      "species": "Deer",
      "hunt_type": "Premium Limited Entry",
      "residency": "Nonresident",
      "points": "29",
      "draw_pool": "standard",
      "draw_system_type": "PREFERENCE_GENERAL_SEASON_BUCK_DEER",
      "algorithm_status": "IN_SCOPE_MODEL_PENDING",
      "reason": "General-season buck deer uses a preference-point model and only promotes rows with valid source history, quota, and modeled preference probabilities.",
      "model_strategy": "",
      "preference_model_valid": "",
      "p_draw": "",
      "p_draw_pct": "",
      "p_preference_draw": "",
      "quota_2026_total": "1"
    },
    {
      "hunt_code": "DB1009",
      "hunt_name": "Henry Mtns (Management Buck Deer)",
      "species": "Deer",
      "hunt_type": "Premium Limited Entry",
      "residency": "Nonresident",
      "points": "30",
      "draw_pool": "standard",
      "draw_system_type": "PREFERENCE_GENERAL_SEASON_BUCK_DEER",
      "algorithm_status": "IN_SCOPE_MODEL_PENDING",
      "reason": "General-season buck deer uses a preference-point model and only promotes rows with valid source history, quota, and modeled preference probabilities.",
      "model_strategy": "",
      "preference_model_valid": "",
      "p_draw": "",
      "p_draw_pct": "",
      "p_preference_draw": "",
      "quota_2026_total": "1"
    },
    {
      "hunt_code": "DB1009",
      "hunt_name": "Henry Mtns (Management Buck Deer)",
      "species": "Deer",
      "hunt_type": "Premium Limited Entry",
      "residency": "Nonresident",
      "points": "31",
      "draw_pool": "standard",
      "draw_system_type": "PREFERENCE_GENERAL_SEASON_BUCK_DEER",
      "algorithm_status": "IN_SCOPE_MODEL_PENDING",
      "reason": "General-season buck deer uses a preference-point model and only promotes rows with valid source history, quota, and modeled preference probabilities.",
      "model_strategy": "",
      "preference_model_valid": "",
      "p_draw": "",
      "p_draw_pct": "",
      "p_preference_draw": "",
      "quota_2026_total": "1"
    }
  ]
}